Workbook

Sheet README
B1: Global LNG Liquefaction (Export) Capacity by Terminal by Year
B2: Nameplate capacity in Mtpa · 2010–2025
B4: WHAT THIS IS
B5: Year-by-year nameplate liquefaction (LNG export) capacity for every operational export terminal worldwide, from 2010 to 2025. "Nameplate" = design/rated capacity in million tonnes per annum (Mtpa).
B7: SOURCE
B8: IGU (International Gas Union) World LNG Report 2026 — Appendix 1: "Table of Global Liquefaction Plants, end-2025" (train-level nameplate capacity, start year, technology, ownership).
B9: GIIGNL 2026 Annual Report — used for cross-validation. It reports global liquefaction capacity of 524 MTPA across 24 exporting countries at end-2025, consistent with the IGU total of 524.6 Mtpa used here.
B11: SHEETS
B12: • Terminal x Year — one row per export terminal; columns 2010–2025 show operational nameplate capacity as of each year-end. THE MAIN DELIVERABLE.
B13: • Country x Year — the same series aggregated to the 26 exporting countries.
B14: • Train detail — the underlying train-by-train records (country, plant, train, technology, start year, capacity, ownership). All year figures are SUMIFS formulas over this sheet.
B15: • Under construction — IGU Appendix 2 (plants sanctioned / under construction, end-2025). Reference only; NOT included in the 2010–2025 series.
... B27: Built 2026-07-31 from user-provided reports. Global end-2025 total: 524.6 Mtpa across 55 terminals / 26 countries / 180 trains.

Sheet Monthly outages (Mtpa)
A1: TIME | D1: Algeria | H1: Angola | I1: Australia | S1: Brunei | T1: Cameroon | U1: Canada | V1: China | W1: Congo | Y1: Egypt | AA1: Equatorial Guinea | AB1: Indonesia | AE1: Malaysia | AH1: Mauritania | AI1: Mexico | AK1: Mozambique | AL1: Nigeria | AM1: Norway | AO1: Oman | AP1: Papua New Guinea | AQ1: Peru | AR1: Qatar | AS1: Russia | AX1: Trinidad and Tobago | AY1: UAE | AZ1: United States | BI1: Yemen
A2: Month | B2: MonthKey | C2: Total offline | D2: Arzew GL1Z | E2: Arzew GL2Z | F2: Arzew GL3Z (Gassi Touil) | G2: Skikda GL1K | H2: Angola LNG | I2: Australia Pacific LNG | J2: Darwin LNG | K2: GLNG | L2: Gorgon LNG | M2: Ichthys LNG | N2: North West Shelf LNG | O2: Pluto LNG | P2: Prelude FLNG | Q2: Queensland Curtis LNG | R2: Wheatstone LNG | S2: Brunei LNG | T2: Cameroon FLNG | U2: LNG Canada | V2: Inland facilities | W2: Congo Marine XII FLNG | X2: Congo Nguya FLNG | Y2: Damietta LNG | Z2: Egyptian LNG (Idku) | AA2: EG LNG | AB2: Bontang LNG | AC2: Donggi- Senoro LNG | AD2: Tangguh LNG | AE2: MLNG | AF2: Petronas FLNG 1 Satu | AG2: Petronas FLNG 2 Rotan | AH2: Tortue/ Ahmeyim FLNG | AI2: Altamira LNG | AJ2: Energia Costa Azul (ECA) | AK2: Coral South FLNG | AL2: NLNG | AM2: Nordic LNG | AN2: Snohvit LNG | AO2: Oman LNG | AP2: PNG LNG | AQ2: Peru LNG | AR2: QatarGas LNG | AS2: Arctic LNG 2 | AT2: Portovaya LNG | AU2: Sakhalin 2 | AV2: Vysotsk LNG | AW2: Yamal LNG | AX2: Atlantic LNG | AY2: Adgas LNG | AZ2: Calcasieu Pass LNG | BA2: Cameron LNG | BB2: Corpus Christi LNG | BC2: Cove Point LNG | BD2: Elba Island LNG | BE2: Freeport LNG | BF2: Golden Pass LNG | BG2: Plaquemines LNG | BH2: Sabine Pass LNG | BI2: Yemen LNG
A3: 40179 | B3: 201001 | C3: =SUM(D3:BI3) -> 8 | D3: =SUMIFS('Outages (event ledger)'!$H$2:$H$65,'Outages (event ledger)'!$A$2:$A$65,D$2,'Outages (event ledger)'!$E$2:$E$65,"<="&$B3,'Outages (event ledger)'!$G$2:$G$65,">="&$B3) -> 0 | E3: =SUMIFS('Outages (event ledger)'!$H$2:$H$65,'Outages (event ledger)'!$A$2:$A$65,E$2,'Outages (event ledger)'!$E$2:$E$65,"<="&$B3,'Outages (event ledger)'!$G$2:$G$65,">="&$B3) -> 0 | F3: =SUMIFS('Outages (event ledger)'!$H$2:$H$65,'Outages (event ledger)'!$A$2:$A$65,F$2,'Outages (event ledger)'!$E$2:$E$65,"<="&$B3,'Outages (event ledger)'!$G$2:$G$65,">="&$B3) -> 0 | G3: =SUMIFS('Outages (event ledger)'!$H$2:$H$65,'Outages (event ledger)'!$A$2:$A$65,G$2,'Outages (event ledger)'!$E$2:$E$65,"<="&$B3,'Outages (event ledger)'!$G$2:$G$65,">="&$B3) -> 0 | H3: =SUMIFS('Outages (event ledger)'!$H$2:$H$65,'Outages (event ledger)'!$A$2:$A$65,H$2,'Outages (event ledger)'!$E$2:$E$65,"<="&$B3,'Outages (event ledger)'!$G$2:$G$65,">="&$B3) -> 0 | I3: =SUMIFS('Outages (event ledger)'!$H$2:$H$65,'Outages (event ledger)'!$A$2:$A$65,I$2,'Outages (event ledger)'!$E$2:$E$65,"<="&$B3,'Outages (event ledger)'!$G$2:$G$65,">="&$B3) -> 0 | J3: =SUMIFS('Outages (event ledger)'!$H$2:$H$65,'Outages (event ledger)'!$A$2:$A$65,J$2,'Outages (event ledger)'!$E$2:$E$65,"<="&$B3,'Outages (event ledger)'!$G$2:$G$65,">="&$B3) -> 0 | K3: =SUMIFS('Outages (event ledger)'!$H$2:$H$65,'Outages (event ledger)'!$A$2:$A$65,K$2,'Outages (event ledger)'!$E$2:$E$65,"<="&$B3,'Outages (event ledger)'!$G$2:$G$65,">="&$B3) -> 0 | ... BI3: =SUMIFS('Outages (event ledger)'!$H$2:$H$65,'Outages (event ledger)'!$A$2:$A$65,BI$2,'Outages (event ledger)'!$E$2:$E$65,"<="&$B3,'Outages (event ledger)'!$G$2:$G$65,">="&$B3) -> 0
A4: 40210 | B4: 201002 | C4: =SUM(D4:BI4) -> 8 | D4: =SUMIFS('Outages (event ledger)'!$H$2:$H$65,'Outages (event ledger)'!$A$2:$A$65,D$2,'Outages (event ledger)'!$E$2:$E$65,"<="&$B4,'Outages (event ledger)'!$G$2:$G$65,">="&$B4) -> 0 | E4: =SUMIFS('Outages (event ledger)'!$H$2:$H$65,'Outages (event ledger)'!$A$2:$A$65,E$2,'Outages (event ledger)'!$E$2:$E$65,"<="&$B4,'Outages (event ledger)'!$G$2:$G$65,">="&$B4) -> 0 | F4: =SUMIFS('Outages (event ledger)'!$H$2:$H$65,'Outages (event ledger)'!$A$2:$A$65,F$2,'Outages (event ledger)'!$E$2:$E$65,"<="&$B4,'Outages (event ledger)'!$G$2:$G$65,">="&$B4) -> 0 | G4: =SUMIFS('Outages (event ledger)'!$H$2:$H$65,'Outages (event ledger)'!$A$2:$A$65,G$2,'Outages (event ledger)'!$E$2:$E$65,"<="&$B4,'Outages (event ledger)'!$G$2:$G$65,">="&$B4) -> 0 | H4: =SUMIFS('Outages (event ledger)'!$H$2:$H$65,'Outages (event ledger)'!$A$2:$A$65,H$2,'Outages (event ledger)'!$E$2:$E$65,"<="&$B4,'Outages (event ledger)'!$G$2:$G$65,">="&$B4) -> 0 | I4: =SUMIFS('Outages (event ledger)'!$H$2:$H$65,'Outages (event ledger)'!$A$2:$A$65,I$2,'Outages (event ledger)'!$E$2:$E$65,"<="&$B4,'Outages (event ledger)'!$G$2:$G$65,">="&$B4) -> 0 | J4: =SUMIFS('Outages (event ledger)'!$H$2:$H$65,'Outages (event ledger)'!$A$2:$A$65,J$2,'Outages (event ledger)'!$E$2:$E$65,"<="&$B4,'Outages (event ledger)'!$G$2:$G$65,">="&$B4) -> 0 | K4: =SUMIFS('Outages (event ledger)'!$H$2:$H$65,'Outages (event ledger)'!$A$2:$A$65,K$2,'Outages (event ledger)'!$E$2:$E$65,"<="&$B4,'Outages (event ledger)'!$G$2:$G$65,">="&$B4) -> 0 | ... BI4: =SUMIFS('Outages (event ledger)'!$H$2:$H$65,'Outages (event ledger)'!$A$2:$A$65,BI$2,'Outages (event ledger)'!$E$2:$E$65,"<="&$B4,'Outages (event ledger)'!$G$2:$G$65,">="&$B4) -> 0
A5: 40238 | B5: 201003 | C5: =SUM(D5:BI5) -> 8 | D5: =SUMIFS('Outages (event ledger)'!$H$2:$H$65,'Outages (event ledger)'!$A$2:$A$65,D$2,'Outages (event ledger)'!$E$2:$E$65,"<="&$B5,'Outages (event ledger)'!$G$2:$G$65,">="&$B5) -> 0 | E5: =SUMIFS('Outages (event ledger)'!$H$2:$H$65,'Outages (event ledger)'!$A$2:$A$65,E$2,'Outages (event ledger)'!$E$2:$E$65,"<="&$B5,'Outages (event ledger)'!$G$2:$G$65,">="&$B5) -> 0 | F5: =SUMIFS('Outages (event ledger)'!$H$2:$H$65,'Outages (event ledger)'!$A$2:$A$65,F$2,'Outages (event ledger)'!$E$2:$E$65,"<="&$B5,'Outages (event ledger)'!$G$2:$G$65,">="&$B5) -> 0 | G5: =SUMIFS('Outages (event ledger)'!$H$2:$H$65,'Outages (event ledger)'!$A$2:$A$65,G$2,'Outages (event ledger)'!$E$2:$E$65,"<="&$B5,'Outages (event ledger)'!$G$2:$G$65,">="&$B5) -> 0 | H5: =SUMIFS('Outages (event ledger)'!$H$2:$H$65,'Outages (event ledger)'!$A$2:$A$65,H$2,'Outages (event ledger)'!$E$2:$E$65,"<="&$B5,'Outages (event ledger)'!$G$2:$G$65,">="&$B5) -> 0 | I5: =SUMIFS('Outages (event ledger)'!$H$2:$H$65,'Outages (event ledger)'!$A$2:$A$65,I$2,'Outages (event ledger)'!$E$2:$E$65,"<="&$B5,'Outages (event ledger)'!$G$2:$G$65,">="&$B5) -> 0 | J5: =SUMIFS('Outages (event ledger)'!$H$2:$H$65,'Outages (event ledger)'!$A$2:$A$65,J$2,'Outages (event ledger)'!$E$2:$E$65,"<="&$B5,'Outages (event ledger)'!$G$2:$G$65,">="&$B5) -> 0 | K5: =SUMIFS('Outages (event ledger)'!$H$2:$H$65,'Outages (event ledger)'!$A$2:$A$65,K$2,'Outages (event ledger)'!$E$2:$E$65,"<="&$B5,'Outages (event ledger)'!$G$2:$G$65,">="&$B5) -> 0 | ... BI5: =SUMIFS('Outages (event ledger)'!$H$2:$H$65,'Outages (event ledger)'!$A$2:$A$65,BI$2,'Outages (event ledger)'!$E$2:$E$65,"<="&$B5,'Outages (event ledger)'!$G$2:$G$65,">="&$B5) -> 0
A6: 40269 | B6: 201004 | C6: =SUM(D6:BI6) -> 8 | D6: =SUMIFS('Outages (event ledger)'!$H$2:$H$65,'Outages (event ledger)'!$A$2:$A$65,D$2,'Outages (event ledger)'!$E$2:$E$65,"<="&$B6,'Outages (event ledger)'!$G$2:$G$65,">="&$B6) -> 0 | E6: =SUMIFS('Outages (event ledger)'!$H$2:$H$65,'Outages (event ledger)'!$A$2:$A$65,E$2,'Outages (event ledger)'!$E$2:$E$65,"<="&$B6,'Outages (event ledger)'!$G$2:$G$65,">="&$B6) -> 0 | F6: =SUMIFS('Outages (event ledger)'!$H$2:$H$65,'Outages (event ledger)'!$A$2:$A$65,F$2,'Outages (event ledger)'!$E$2:$E$65,"<="&$B6,'Outages (event ledger)'!$G$2:$G$65,">="&$B6) -> 0 | G6: =SUMIFS('Outages (event ledger)'!$H$2:$H$65,'Outages (event ledger)'!$A$2:$A$65,G$2,'Outages (event ledger)'!$E$2:$E$65,"<="&$B6,'Outages (event ledger)'!$G$2:$G$65,">="&$B6) -> 0 | H6: =SUMIFS('Outages (event ledger)'!$H$2:$H$65,'Outages (event ledger)'!$A$2:$A$65,H$2,'Outages (event ledger)'!$E$2:$E$65,"<="&$B6,'Outages (event ledger)'!$G$2:$G$65,">="&$B6) -> 0 | I6: =SUMIFS('Outages (event ledger)'!$H$2:$H$65,'Outages (event ledger)'!$A$2:$A$65,I$2,'Outages (event ledger)'!$E$2:$E$65,"<="&$B6,'Outages (event ledger)'!$G$2:$G$65,">="&$B6) -> 0 | J6: =SUMIFS('Outages (event ledger)'!$H$2:$H$65,'Outages (event ledger)'!$A$2:$A$65,J$2,'Outages (event ledger)'!$E$2:$E$65,"<="&$B6,'Outages (event ledger)'!$G$2:$G$65,">="&$B6) -> 0 | K6: =SUMIFS('Outages (event ledger)'!$H$2:$H$65,'Outages (event ledger)'!$A$2:$A$65,K$2,'Outages (event ledger)'!$E$2:$E$65,"<="&$B6,'Outages (event ledger)'!$G$2:$G$65,">="&$B6) -> 0 | ... BI6: =SUMIFS('Outages (event ledger)'!$H$2:$H$65,'Outages (event ledger)'!$A$2:$A$65,BI$2,'Outages (event ledger)'!$E$2:$E$65,"<="&$B6,'Outages (event ledger)'!$G$2:$G$65,">="&$B6) -> 0
A7: 40299 | B7: 201005 | C7: =SUM(D7:BI7) -> 8 | D7: =SUMIFS('Outages (event ledger)'!$H$2:$H$65,'Outages (event ledger)'!$A$2:$A$65,D$2,'Outages (event ledger)'!$E$2:$E$65,"<="&$B7,'Outages (event ledger)'!$G$2:$G$65,">="&$B7) -> 0 | E7: =SUMIFS('Outages (event ledger)'!$H$2:$H$65,'Outages (event ledger)'!$A$2:$A$65,E$2,'Outages (event ledger)'!$E$2:$E$65,"<="&$B7,'Outages (event ledger)'!$G$2:$G$65,">="&$B7) -> 0 | F7: =SUMIFS('Outages (event ledger)'!$H$2:$H$65,'Outages (event ledger)'!$A$2:$A$65,F$2,'Outages (event ledger)'!$E$2:$E$65,"<="&$B7,'Outages (event ledger)'!$G$2:$G$65,">="&$B7) -> 0 | G7: =SUMIFS('Outages (event ledger)'!$H$2:$H$65,'Outages (event ledger)'!$A$2:$A$65,G$2,'Outages (event ledger)'!$E$2:$E$65,"<="&$B7,'Outages (event ledger)'!$G$2:$G$65,">="&$B7) -> 0 | H7: =SUMIFS('Outages (event ledger)'!$H$2:$H$65,'Outages (event ledger)'!$A$2:$A$65,H$2,'Outages (event ledger)'!$E$2:$E$65,"<="&$B7,'Outages (event ledger)'!$G$2:$G$65,">="&$B7) -> 0 | I7: =SUMIFS('Outages (event ledger)'!$H$2:$H$65,'Outages (event ledger)'!$A$2:$A$65,I$2,'Outages (event ledger)'!$E$2:$E$65,"<="&$B7,'Outages (event ledger)'!$G$2:$G$65,">="&$B7) -> 0 | J7: =SUMIFS('Outages (event ledger)'!$H$2:$H$65,'Outages (event ledger)'!$A$2:$A$65,J$2,'Outages (event ledger)'!$E$2:$E$65,"<="&$B7,'Outages (event ledger)'!$G$2:$G$65,">="&$B7) -> 0 | K7: =SUMIFS('Outages (event ledger)'!$H$2:$H$65,'Outages (event ledger)'!$A$2:$A$65,K$2,'Outages (event ledger)'!$E$2:$E$65,"<="&$B7,'Outages (event ledger)'!$G$2:$G$65,">="&$B7) -> 0 | ... BI7: =SUMIFS('Outages (event ledger)'!$H$2:$H$65,'Outages (event ledger)'!$A$2:$A$65,BI$2,'Outages (event ledger)'!$E$2:$E$65,"<="&$B7,'Outages (event ledger)'!$G$2:$G$65,">="&$B7) -> 0
A8: 40330 | B8: 201006 | C8: =SUM(D8:BI8) -> 8 | D8: =SUMIFS('Outages (event ledger)'!$H$2:$H$65,'Outages (event ledger)'!$A$2:$A$65,D$2,'Outages (event ledger)'!$E$2:$E$65,"<="&$B8,'Outages (event ledger)'!$G$2:$G$65,">="&$B8) -> 0 | E8: =SUMIFS('Outages (event ledger)'!$H$2:$H$65,'Outages (event ledger)'!$A$2:$A$65,E$2,'Outages (event ledger)'!$E$2:$E$65,"<="&$B8,'Outages (event ledger)'!$G$2:$G$65,">="&$B8) -> 0 | F8: =SUMIFS('Outages (event ledger)'!$H$2:$H$65,'Outages (event ledger)'!$A$2:$A$65,F$2,'Outages (event ledger)'!$E$2:$E$65,"<="&$B8,'Outages (event ledger)'!$G$2:$G$65,">="&$B8) -> 0 | G8: =SUMIFS('Outages (event ledger)'!$H$2:$H$65,'Outages (event ledger)'!$A$2:$A$65,G$2,'Outages (event ledger)'!$E$2:$E$65,"<="&$B8,'Outages (event ledger)'!$G$2:$G$65,">="&$B8) -> 0 | H8: =SUMIFS('Outages (event ledger)'!$H$2:$H$65,'Outages (event ledger)'!$A$2:$A$65,H$2,'Outages (event ledger)'!$E$2:$E$65,"<="&$B8,'Outages (event ledger)'!$G$2:$G$65,">="&$B8) -> 0 | I8: =SUMIFS('Outages (event ledger)'!$H$2:$H$65,'Outages (event ledger)'!$A$2:$A$65,I$2,'Outages (event ledger)'!$E$2:$E$65,"<="&$B8,'Outages (event ledger)'!$G$2:$G$65,">="&$B8) -> 0 | J8: =SUMIFS('Outages (event ledger)'!$H$2:$H$65,'Outages (event ledger)'!$A$2:$A$65,J$2,'Outages (event ledger)'!$E$2:$E$65,"<="&$B8,'Outages (event ledger)'!$G$2:$G$65,">="&$B8) -> 0 | K8: =SUMIFS('Outages (event ledger)'!$H$2:$H$65,'Outages (event ledger)'!$A$2:$A$65,K$2,'Outages (event ledger)'!$E$2:$E$65,"<="&$B8,'Outages (event ledger)'!$G$2:$G$65,">="&$B8) -> 0 | ... BI8: =SUMIFS('Outages (event ledger)'!$H$2:$H$65,'Outages (event ledger)'!$A$2:$A$65,BI$2,'Outages (event ledger)'!$E$2:$E$65,"<="&$B8,'Outages (event ledger)'!$G$2:$G$65,">="&$B8) -> 0
A9: 40360 | B9: 201007 | C9: =SUM(D9:BI9) -> 8 | D9: =SUMIFS('Outages (event ledger)'!$H$2:$H$65,'Outages (event ledger)'!$A$2:$A$65,D$2,'Outages (event ledger)'!$E$2:$E$65,"<="&$B9,'Outages (event ledger)'!$G$2:$G$65,">="&$B9) -> 0 | E9: =SUMIFS('Outages (event ledger)'!$H$2:$H$65,'Outages (event ledger)'!$A$2:$A$65,E$2,'Outages (event ledger)'!$E$2:$E$65,"<="&$B9,'Outages (event ledger)'!$G$2:$G$65,">="&$B9) -> 0 | F9: =SUMIFS('Outages (event ledger)'!$H$2:$H$65,'Outages (event ledger)'!$A$2:$A$65,F$2,'Outages (event ledger)'!$E$2:$E$65,"<="&$B9,'Outages (event ledger)'!$G$2:$G$65,">="&$B9) -> 0 | G9: =SUMIFS('Outages (event ledger)'!$H$2:$H$65,'Outages (event ledger)'!$A$2:$A$65,G$2,'Outages (event ledger)'!$E$2:$E$65,"<="&$B9,'Outages (event ledger)'!$G$2:$G$65,">="&$B9) -> 0 | H9: =SUMIFS('Outages (event ledger)'!$H$2:$H$65,'Outages (event ledger)'!$A$2:$A$65,H$2,'Outages (event ledger)'!$E$2:$E$65,"<="&$B9,'Outages (event ledger)'!$G$2:$G$65,">="&$B9) -> 0 | I9: =SUMIFS('Outages (event ledger)'!$H$2:$H$65,'Outages (event ledger)'!$A$2:$A$65,I$2,'Outages (event ledger)'!$E$2:$E$65,"<="&$B9,'Outages (event ledger)'!$G$2:$G$65,">="&$B9) -> 0 | J9: =SUMIFS('Outages (event ledger)'!$H$2:$H$65,'Outages (event ledger)'!$A$2:$A$65,J$2,'Outages (event ledger)'!$E$2:$E$65,"<="&$B9,'Outages (event ledger)'!$G$2:$G$65,">="&$B9) -> 0 | K9: =SUMIFS('Outages (event ledger)'!$H$2:$H$65,'Outages (event ledger)'!$A$2:$A$65,K$2,'Outages (event ledger)'!$E$2:$E$65,"<="&$B9,'Outages (event ledger)'!$G$2:$G$65,">="&$B9) -> 0 | ... BI9: =SUMIFS('Outages (event ledger)'!$H$2:$H$65,'Outages (event ledger)'!$A$2:$A$65,BI$2,'Outages (event ledger)'!$E$2:$E$65,"<="&$B9,'Outages (event ledger)'!$G$2:$G$65,">="&$B9) -> 0
A10: 40391 | B10: 201008 | C10: =SUM(D10:BI10) -> 8 | D10: =SUMIFS('Outages (event ledger)'!$H$2:$H$65,'Outages (event ledger)'!$A$2:$A$65,D$2,'Outages (event ledger)'!$E$2:$E$65,"<="&$B10,'Outages (event ledger)'!$G$2:$G$65,">="&$B10) -> 0 | E10: =SUMIFS('Outages (event ledger)'!$H$2:$H$65,'Outages (event ledger)'!$A$2:$A$65,E$2,'Outages (event ledger)'!$E$2:$E$65,"<="&$B10,'Outages (event ledger)'!$G$2:$G$65,">="&$B10) -> 0 | F10: =SUMIFS('Outages (event ledger)'!$H$2:$H$65,'Outages (event ledger)'!$A$2:$A$65,F$2,'Outages (event ledger)'!$E$2:$E$65,"<="&$B10,'Outages (event ledger)'!$G$2:$G$65,">="&$B10) -> 0 | G10: =SUMIFS('Outages (event ledger)'!$H$2:$H$65,'Outages (event ledger)'!$A$2:$A$65,G$2,'Outages (event ledger)'!$E$2:$E$65,"<="&$B10,'Outages (event ledger)'!$G$2:$G$65,">="&$B10) -> 0 | H10: =SUMIFS('Outages (event ledger)'!$H$2:$H$65,'Outages (event ledger)'!$A$2:$A$65,H$2,'Outages (event ledger)'!$E$2:$E$65,"<="&$B10,'Outages (event ledger)'!$G$2:$G$65,">="&$B10) -> 0 | I10: =SUMIFS('Outages (event ledger)'!$H$2:$H$65,'Outages (event ledger)'!$A$2:$A$65,I$2,'Outages (event ledger)'!$E$2:$E$65,"<="&$B10,'Outages (event ledger)'!$G$2:$G$65,">="&$B10) -> 0 | J10: =SUMIFS('Outages (event ledger)'!$H$2:$H$65,'Outages (event ledger)'!$A$2:$A$65,J$2,'Outages (event ledger)'!$E$2:$E$65,"<="&$B10,'Outages (event ledger)'!$G$2:$G$65,">="&$B10) -> 0 | K10: =SUMIFS('Outages (event ledger)'!$H$2:$H$65,'Outages (event ledger)'!$A$2:$A$65,K$2,'Outages (event ledger)'!$E$2:$E$65,"<="&$B10,'Outages (event ledger)'!$G$2:$G$65,">="&$B10) -> 0 | ... BI10: =SUMIFS('Outages (event ledger)'!$H$2:$H$65,'Outages (event ledger)'!$A$2:$A$65,BI$2,'Outages (event ledger)'!$E$2:$E$65,"<="&$B10,'Outages (event ledger)'!$G$2:$G$65,">="&$B10) -> 0
A11: 40422 | B11: 201009 | C11: =SUM(D11:BI11) -> 8 | D11: =SUMIFS('Outages (event ledger)'!$H$2:$H$65,'Outages (event ledger)'!$A$2:$A$65,D$2,'Outages (event ledger)'!$E$2:$E$65,"<="&$B11,'Outages (event ledger)'!$G$2:$G$65,">="&$B11) -> 0 | E11: =SUMIFS('Outages (event ledger)'!$H$2:$H$65,'Outages (event ledger)'!$A$2:$A$65,E$2,'Outages (event ledger)'!$E$2:$E$65,"<="&$B11,'Outages (event ledger)'!$G$2:$G$65,">="&$B11) -> 0 | F11: =SUMIFS('Outages (event ledger)'!$H$2:$H$65,'Outages (event ledger)'!$A$2:$A$65,F$2,'Outages (event ledger)'!$E$2:$E$65,"<="&$B11,'Outages (event ledger)'!$G$2:$G$65,">="&$B11) -> 0 | G11: =SUMIFS('Outages (event ledger)'!$H$2:$H$65,'Outages (event ledger)'!$A$2:$A$65,G$2,'Outages (event ledger)'!$E$2:$E$65,"<="&$B11,'Outages (event ledger)'!$G$2:$G$65,">="&$B11) -> 0 | H11: =SUMIFS('Outages (event ledger)'!$H$2:$H$65,'Outages (event ledger)'!$A$2:$A$65,H$2,'Outages (event ledger)'!$E$2:$E$65,"<="&$B11,'Outages (event ledger)'!$G$2:$G$65,">="&$B11) -> 0 | I11: =SUMIFS('Outages (event ledger)'!$H$2:$H$65,'Outages (event ledger)'!$A$2:$A$65,I$2,'Outages (event ledger)'!$E$2:$E$65,"<="&$B11,'Outages (event ledger)'!$G$2:$G$65,">="&$B11) -> 0 | J11: =SUMIFS('Outages (event ledger)'!$H$2:$H$65,'Outages (event ledger)'!$A$2:$A$65,J$2,'Outages (event ledger)'!$E$2:$E$65,"<="&$B11,'Outages (event ledger)'!$G$2:$G$65,">="&$B11) -> 0 | K11: =SUMIFS('Outages (event ledger)'!$H$2:$H$65,'Outages (event ledger)'!$A$2:$A$65,K$2,'Outages (event ledger)'!$E$2:$E$65,"<="&$B11,'Outages (event ledger)'!$G$2:$G$65,">="&$B11) -> 0 | ... BI11: =SUMIFS('Outages (event ledger)'!$H$2:$H$65,'Outages (event ledger)'!$A$2:$A$65,BI$2,'Outages (event ledger)'!$E$2:$E$65,"<="&$B11,'Outages (event ledger)'!$G$2:$G$65,">="&$B11) -> 0
A12: 40452 | B12: 201010 | C12: =SUM(D12:BI12) -> 8 | D12: =SUMIFS('Outages (event ledger)'!$H$2:$H$65,'Outages (event ledger)'!$A$2:$A$65,D$2,'Outages (event ledger)'!$E$2:$E$65,"<="&$B12,'Outages (event ledger)'!$G$2:$G$65,">="&$B12) -> 0 | E12: =SUMIFS('Outages (event ledger)'!$H$2:$H$65,'Outages (event ledger)'!$A$2:$A$65,E$2,'Outages (event ledger)'!$E$2:$E$65,"<="&$B12,'Outages (event ledger)'!$G$2:$G$65,">="&$B12) -> 0 | F12: =SUMIFS('Outages (event ledger)'!$H$2:$H$65,'Outages (event ledger)'!$A$2:$A$65,F$2,'Outages (event ledger)'!$E$2:$E$65,"<="&$B12,'Outages (event ledger)'!$G$2:$G$65,">="&$B12) -> 0 | G12: =SUMIFS('Outages (event ledger)'!$H$2:$H$65,'Outages (event ledger)'!$A$2:$A$65,G$2,'Outages (event ledger)'!$E$2:$E$65,"<="&$B12,'Outages (event ledger)'!$G$2:$G$65,">="&$B12) -> 0 | H12: =SUMIFS('Outages (event ledger)'!$H$2:$H$65,'Outages (event ledger)'!$A$2:$A$65,H$2,'Outages (event ledger)'!$E$2:$E$65,"<="&$B12,'Outages (event ledger)'!$G$2:$G$65,">="&$B12) -> 0 | I12: =SUMIFS('Outages (event ledger)'!$H$2:$H$65,'Outages (event ledger)'!$A$2:$A$65,I$2,'Outages (event ledger)'!$E$2:$E$65,"<="&$B12,'Outages (event ledger)'!$G$2:$G$65,">="&$B12) -> 0 | J12: =SUMIFS('Outages (event ledger)'!$H$2:$H$65,'Outages (event ledger)'!$A$2:$A$65,J$2,'Outages (event ledger)'!$E$2:$E$65,"<="&$B12,'Outages (event ledger)'!$G$2:$G$65,">="&$B12) -> 0 | K12: =SUMIFS('Outages (event ledger)'!$H$2:$H$65,'Outages (event ledger)'!$A$2:$A$65,K$2,'Outages (event ledger)'!$E$2:$E$65,"<="&$B12,'Outages (event ledger)'!$G$2:$G$65,">="&$B12) -> 0 | ... BI12: =SUMIFS('Outages (event ledger)'!$H$2:$H$65,'Outages (event ledger)'!$A$2:$A$65,BI$2,'Outages (event ledger)'!$E$2:$E$65,"<="&$B12,'Outages (event ledger)'!$G$2:$G$65,">="&$B12) -> 0
A13: 40483 | B13: 201011 | C13: =SUM(D13:BI13) -> 8 | D13: =SUMIFS('Outages (event ledger)'!$H$2:$H$65,'Outages (event ledger)'!$A$2:$A$65,D$2,'Outages (event ledger)'!$E$2:$E$65,"<="&$B13,'Outages (event ledger)'!$G$2:$G$65,">="&$B13) -> 0 | E13: =SUMIFS('Outages (event ledger)'!$H$2:$H$65,'Outages (event ledger)'!$A$2:$A$65,E$2,'Outages (event ledger)'!$E$2:$E$65,"<="&$B13,'Outages (event ledger)'!$G$2:$G$65,">="&$B13) -> 0 | F13: =SUMIFS('Outages (event ledger)'!$H$2:$H$65,'Outages (event ledger)'!$A$2:$A$65,F$2,'Outages (event ledger)'!$E$2:$E$65,"<="&$B13,'Outages (event ledger)'!$G$2:$G$65,">="&$B13) -> 0 | G13: =SUMIFS('Outages (event ledger)'!$H$2:$H$65,'Outages (event ledger)'!$A$2:$A$65,G$2,'Outages (event ledger)'!$E$2:$E$65,"<="&$B13,'Outages (event ledger)'!$G$2:$G$65,">="&$B13) -> 0 | H13: =SUMIFS('Outages (event ledger)'!$H$2:$H$65,'Outages (event ledger)'!$A$2:$A$65,H$2,'Outages (event ledger)'!$E$2:$E$65,"<="&$B13,'Outages (event ledger)'!$G$2:$G$65,">="&$B13) -> 0 | I13: =SUMIFS('Outages (event ledger)'!$H$2:$H$65,'Outages (event ledger)'!$A$2:$A$65,I$2,'Outages (event ledger)'!$E$2:$E$65,"<="&$B13,'Outages (event ledger)'!$G$2:$G$65,">="&$B13) -> 0 | J13: =SUMIFS('Outages (event ledger)'!$H$2:$H$65,'Outages (event ledger)'!$A$2:$A$65,J$2,'Outages (event ledger)'!$E$2:$E$65,"<="&$B13,'Outages (event ledger)'!$G$2:$G$65,">="&$B13) -> 0 | K13: =SUMIFS('Outages (event ledger)'!$H$2:$H$65,'Outages (event ledger)'!$A$2:$A$65,K$2,'Outages (event ledger)'!$E$2:$E$65,"<="&$B13,'Outages (event ledger)'!$G$2:$G$65,">="&$B13) -> 0 | ... BI13: =SUMIFS('Outages (event ledger)'!$H$2:$H$65,'Outages (event ledger)'!$A$2:$A$65,BI$2,'Outages (event ledger)'!$E$2:$E$65,"<="&$B13,'Outages (event ledger)'!$G$2:$G$65,">="&$B13) -> 0
A14: 40513 | B14: 201012 | C14: =SUM(D14:BI14) -> 8 | D14: =SUMIFS('Outages (event ledger)'!$H$2:$H$65,'Outages (event ledger)'!$A$2:$A$65,D$2,'Outages (event ledger)'!$E$2:$E$65,"<="&$B14,'Outages (event ledger)'!$G$2:$G$65,">="&$B14) -> 0 | E14: =SUMIFS('Outages (event ledger)'!$H$2:$H$65,'Outages (event ledger)'!$A$2:$A$65,E$2,'Outages (event ledger)'!$E$2:$E$65,"<="&$B14,'Outages (event ledger)'!$G$2:$G$65,">="&$B14) -> 0 | F14: =SUMIFS('Outages (event ledger)'!$H$2:$H$65,'Outages (event ledger)'!$A$2:$A$65,F$2,'Outages (event ledger)'!$E$2:$E$65,"<="&$B14,'Outages (event ledger)'!$G$2:$G$65,">="&$B14) -> 0 | G14: =SUMIFS('Outages (event ledger)'!$H$2:$H$65,'Outages (event ledger)'!$A$2:$A$65,G$2,'Outages (event ledger)'!$E$2:$E$65,"<="&$B14,'Outages (event ledger)'!$G$2:$G$65,">="&$B14) -> 0 | H14: =SUMIFS('Outages (event ledger)'!$H$2:$H$65,'Outages (event ledger)'!$A$2:$A$65,H$2,'Outages (event ledger)'!$E$2:$E$65,"<="&$B14,'Outages (event ledger)'!$G$2:$G$65,">="&$B14) -> 0 | I14: =SUMIFS('Outages (event ledger)'!$H$2:$H$65,'Outages (event ledger)'!$A$2:$A$65,I$2,'Outages (event ledger)'!$E$2:$E$65,"<="&$B14,'Outages (event ledger)'!$G$2:$G$65,">="&$B14) -> 0 | J14: =SUMIFS('Outages (event ledger)'!$H$2:$H$65,'Outages (event ledger)'!$A$2:$A$65,J$2,'Outages (event ledger)'!$E$2:$E$65,"<="&$B14,'Outages (event ledger)'!$G$2:$G$65,">="&$B14) -> 0 | K14: =SUMIFS('Outages (event ledger)'!$H$2:$H$65,'Outages (event ledger)'!$A$2:$A$65,K$2,'Outages (event ledger)'!$E$2:$E$65,"<="&$B14,'Outages (event ledger)'!$G$2:$G$65,">="&$B14) -> 0 | ... BI14: =SUMIFS('Outages (event ledger)'!$H$2:$H$65,'Outages (event ledger)'!$A$2:$A$65,BI$2,'Outages (event ledger)'!$E$2:$E$65,"<="&$B14,'Outages (event ledger)'!$G$2:$G$65,">="&$B14) -> 0
... A206: 46357 | B206: 202612 | C206: =SUM(D206:BI206) -> 36.1 | D206: =SUMIFS('Outages (event ledger)'!$H$2:$H$65,'Outages (event ledger)'!$A$2:$A$65,D$2,'Outages (event ledger)'!$E$2:$E$65,"<="&$B206,'Outages (event ledger)'!$G$2:$G$65,">="&$B206) -> 0 | E206: =SUMIFS('Outages (event ledger)'!$H$2:$H$65,'Outages (event ledger)'!$A$2:$A$65,E$2,'Outages (event ledger)'!$E$2:$E$65,"<="&$B206,'Outages (event ledger)'!$G$2:$G$65,">="&$B206) -> 0 | F206: =SUMIFS('Outages (event ledger)'!$H$2:$H$65,'Outages (event ledger)'!$A$2:$A$65,F$2,'Outages (event ledger)'!$E$2:$E$65,"<="&$B206,'Outages (event ledger)'!$G$2:$G$65,">="&$B206) -> 0 | G206: =SUMIFS('Outages (event ledger)'!$H$2:$H$65,'Outages (event ledger)'!$A$2:$A$65,G$2,'Outages (event ledger)'!$E$2:$E$65,"<="&$B206,'Outages (event ledger)'!$G$2:$G$65,">="&$B206) -> 0 | H206: =SUMIFS('Outages (event ledger)'!$H$2:$H$65,'Outages (event ledger)'!$A$2:$A$65,H$2,'Outages (event ledger)'!$E$2:$E$65,"<="&$B206,'Outages (event ledger)'!$G$2:$G$65,">="&$B206) -> 0 | I206: =SUMIFS('Outages (event ledger)'!$H$2:$H$65,'Outages (event ledger)'!$A$2:$A$65,I$2,'Outages (event ledger)'!$E$2:$E$65,"<="&$B206,'Outages (event ledger)'!$G$2:$G$65,">="&$B206) -> 0 | J206: =SUMIFS('Outages (event ledger)'!$H$2:$H$65,'Outages (event ledger)'!$A$2:$A$65,J$2,'Outages (event ledger)'!$E$2:$E$65,"<="&$B206,'Outages (event ledger)'!$G$2:$G$65,">="&$B206) -> 0 | K206: =SUMIFS('Outages (event ledger)'!$H$2:$H$65,'Outages (event ledger)'!$A$2:$A$65,K$2,'Outages (event ledger)'!$E$2:$E$65,"<="&$B206,'Outages (event ledger)'!$G$2:$G$65,">="&$B206) -> 0 | ... BI206: =SUMIFS('Outages (event ledger)'!$H$2:$H$65,'Outages (event ledger)'!$A$2:$A$65,BI$2,'Outages (event ledger)'!$E$2:$E$65,"<="&$B206,'Outages (event ledger)'!$G$2:$G$65,">="&$B206) -> 6.7
A208: MONTHLY LNG EXPORT CAPACITY OFFLINE (Mtpa), estimated, Jan 2010 – Dec 2026. Each cell = approx nameplate OUT that month, live SUMIFS over "Outages (event ledger)". Hover shaded cells for basis; full notes/sources in ledger.
A209: HEAVILY ESTIMATED. Short trips diluted to a monthly average (peak noted); partial-train events show affected train(s) only. Order-of-magnitude, not precise.
A210: 2026 UPDATE: Ras Laffan (Qatar) — 2 trains destroyed by missile strikes ~Mar 2026 (~12.8 Mtpa), out for years (ongoing). Late-Mar 2026 WA cyclone hit Wheatstone, North West Shelf & Gorgon (mostly brief). Freeport brief May-2026 trip. Ongoing structural shut-ins (Yemen, Trinidad, Bontang, EG LNG) carried forward through 2026.
A211: COVERAGE/SCOPE: discrete unplanned events researched through ~June 2026 (report date late Jul 2026); H2-2026 will miss new events not yet known. Sanctions & planned maintenance excluded. The 2023 Gorgon/Wheatstone strikes logged ~0 (no real output loss). Filter ledger by Type to isolate event-driven vs structural/feedgas.

Sheet Monthly capacity (Mtpa)
A1: TIME | D1: Algeria | H1: Angola | I1: Australia | S1: Brunei | T1: Cameroon | U1: Canada | V1: China | W1: Congo | Y1: Egypt | AA1: Equatorial Guinea | AB1: Indonesia | AE1: Malaysia | AH1: Mauritania | AI1: Mexico | AK1: Mozambique | AL1: Nigeria | AM1: Norway | AO1: Oman | AP1: Papua New Guinea | AQ1: Peru | AR1: Qatar | AS1: Russia | AX1: Trinidad and Tobago | AY1: UAE | AZ1: United States | BI1: Yemen
A2: Month | B2: MonthKey | C2: Global Total | D2: Arzew GL1Z | E2: Arzew GL2Z | F2: Arzew GL3Z (Gassi Touil) | G2: Skikda GL1K | H2: Angola LNG | I2: Australia Pacific LNG | J2: Darwin LNG | K2: GLNG | L2: Gorgon LNG | M2: Ichthys LNG | N2: North West Shelf LNG | O2: Pluto LNG | P2: Prelude FLNG | Q2: Queensland Curtis LNG | R2: Wheatstone LNG | S2: Brunei LNG | T2: Cameroon FLNG | U2: LNG Canada | V2: Inland facilities | W2: Congo Marine XII FLNG | X2: Congo Nguya FLNG | Y2: Damietta LNG | Z2: Egyptian LNG (Idku) | AA2: EG LNG | AB2: Bontang LNG | AC2: Donggi- Senoro LNG | AD2: Tangguh LNG | AE2: MLNG | AF2: Petronas FLNG 1 Satu | AG2: Petronas FLNG 2 Rotan | AH2: Tortue/ Ahmeyim FLNG | AI2: Altamira LNG | AJ2: Energia Costa Azul (ECA) | AK2: Coral South FLNG | AL2: NLNG | AM2: Nordic LNG | AN2: Snohvit LNG | AO2: Oman LNG | AP2: PNG LNG | AQ2: Peru LNG | AR2: QatarGas LNG | AS2: Arctic LNG 2 | AT2: Portovaya LNG | AU2: Sakhalin 2 | AV2: Vysotsk LNG | AW2: Yamal LNG | AX2: Atlantic LNG | AY2: Adgas LNG | AZ2: Calcasieu Pass LNG | BA2: Cameron LNG | BB2: Corpus Christi LNG | BC2: Cove Point LNG | BD2: Elba Island LNG | BE2: Freeport LNG | BF2: Golden Pass LNG | BG2: Plaquemines LNG | BH2: Sabine Pass LNG | BI2: Yemen LNG
A3: 40179 | B3: 201001 | C3: =SUMIFS('Additions (monthly)'!$E$2:$E$106,'Additions (monthly)'!$B$2:$B$106,"<="&$B3) -> 243.22 | D3: =SUMIFS('Additions (monthly)'!$E$2:$E$106,'Additions (monthly)'!$D$2:$D$106,D$2,'Additions (monthly)'!$B$2:$B$106,"<="&$B3) -> 7.9 | E3: =SUMIFS('Additions (monthly)'!$E$2:$E$106,'Additions (monthly)'!$D$2:$D$106,E$2,'Additions (monthly)'!$B$2:$B$106,"<="&$B3) -> 8.4 | F3: =SUMIFS('Additions (monthly)'!$E$2:$E$106,'Additions (monthly)'!$D$2:$D$106,F$2,'Additions (monthly)'!$B$2:$B$106,"<="&$B3) -> 0 | G3: =SUMIFS('Additions (monthly)'!$E$2:$E$106,'Additions (monthly)'!$D$2:$D$106,G$2,'Additions (monthly)'!$B$2:$B$106,"<="&$B3) -> 0 | H3: =SUMIFS('Additions (monthly)'!$E$2:$E$106,'Additions (monthly)'!$D$2:$D$106,H$2,'Additions (monthly)'!$B$2:$B$106,"<="&$B3) -> 0 | I3: =SUMIFS('Additions (monthly)'!$E$2:$E$106,'Additions (monthly)'!$D$2:$D$106,I$2,'Additions (monthly)'!$B$2:$B$106,"<="&$B3) -> 0 | J3: =SUMIFS('Additions (monthly)'!$E$2:$E$106,'Additions (monthly)'!$D$2:$D$106,J$2,'Additions (monthly)'!$B$2:$B$106,"<="&$B3) -> 3.7 | K3: =SUMIFS('Additions (monthly)'!$E$2:$E$106,'Additions (monthly)'!$D$2:$D$106,K$2,'Additions (monthly)'!$B$2:$B$106,"<="&$B3) -> 0 | ... BI3: =SUMIFS('Additions (monthly)'!$E$2:$E$106,'Additions (monthly)'!$D$2:$D$106,BI$2,'Additions (monthly)'!$B$2:$B$106,"<="&$B3) -> 6.7
A4: 40210 | B4: 201002 | C4: =SUMIFS('Additions (monthly)'!$E$2:$E$106,'Additions (monthly)'!$B$2:$B$106,"<="&$B4) -> 243.22 | D4: =SUMIFS('Additions (monthly)'!$E$2:$E$106,'Additions (monthly)'!$D$2:$D$106,D$2,'Additions (monthly)'!$B$2:$B$106,"<="&$B4) -> 7.9 | E4: =SUMIFS('Additions (monthly)'!$E$2:$E$106,'Additions (monthly)'!$D$2:$D$106,E$2,'Additions (monthly)'!$B$2:$B$106,"<="&$B4) -> 8.4 | F4: =SUMIFS('Additions (monthly)'!$E$2:$E$106,'Additions (monthly)'!$D$2:$D$106,F$2,'Additions (monthly)'!$B$2:$B$106,"<="&$B4) -> 0 | G4: =SUMIFS('Additions (monthly)'!$E$2:$E$106,'Additions (monthly)'!$D$2:$D$106,G$2,'Additions (monthly)'!$B$2:$B$106,"<="&$B4) -> 0 | H4: =SUMIFS('Additions (monthly)'!$E$2:$E$106,'Additions (monthly)'!$D$2:$D$106,H$2,'Additions (monthly)'!$B$2:$B$106,"<="&$B4) -> 0 | I4: =SUMIFS('Additions (monthly)'!$E$2:$E$106,'Additions (monthly)'!$D$2:$D$106,I$2,'Additions (monthly)'!$B$2:$B$106,"<="&$B4) -> 0 | J4: =SUMIFS('Additions (monthly)'!$E$2:$E$106,'Additions (monthly)'!$D$2:$D$106,J$2,'Additions (monthly)'!$B$2:$B$106,"<="&$B4) -> 3.7 | K4: =SUMIFS('Additions (monthly)'!$E$2:$E$106,'Additions (monthly)'!$D$2:$D$106,K$2,'Additions (monthly)'!$B$2:$B$106,"<="&$B4) -> 0 | ... BI4: =SUMIFS('Additions (monthly)'!$E$2:$E$106,'Additions (monthly)'!$D$2:$D$106,BI$2,'Additions (monthly)'!$B$2:$B$106,"<="&$B4) -> 6.7
A5: 40238 | B5: 201003 | C5: =SUMIFS('Additions (monthly)'!$E$2:$E$106,'Additions (monthly)'!$B$2:$B$106,"<="&$B5) -> 243.22 | D5: =SUMIFS('Additions (monthly)'!$E$2:$E$106,'Additions (monthly)'!$D$2:$D$106,D$2,'Additions (monthly)'!$B$2:$B$106,"<="&$B5) -> 7.9 | E5: =SUMIFS('Additions (monthly)'!$E$2:$E$106,'Additions (monthly)'!$D$2:$D$106,E$2,'Additions (monthly)'!$B$2:$B$106,"<="&$B5) -> 8.4 | F5: =SUMIFS('Additions (monthly)'!$E$2:$E$106,'Additions (monthly)'!$D$2:$D$106,F$2,'Additions (monthly)'!$B$2:$B$106,"<="&$B5) -> 0 | G5: =SUMIFS('Additions (monthly)'!$E$2:$E$106,'Additions (monthly)'!$D$2:$D$106,G$2,'Additions (monthly)'!$B$2:$B$106,"<="&$B5) -> 0 | H5: =SUMIFS('Additions (monthly)'!$E$2:$E$106,'Additions (monthly)'!$D$2:$D$106,H$2,'Additions (monthly)'!$B$2:$B$106,"<="&$B5) -> 0 | I5: =SUMIFS('Additions (monthly)'!$E$2:$E$106,'Additions (monthly)'!$D$2:$D$106,I$2,'Additions (monthly)'!$B$2:$B$106,"<="&$B5) -> 0 | J5: =SUMIFS('Additions (monthly)'!$E$2:$E$106,'Additions (monthly)'!$D$2:$D$106,J$2,'Additions (monthly)'!$B$2:$B$106,"<="&$B5) -> 3.7 | K5: =SUMIFS('Additions (monthly)'!$E$2:$E$106,'Additions (monthly)'!$D$2:$D$106,K$2,'Additions (monthly)'!$B$2:$B$106,"<="&$B5) -> 0 | ... BI5: =SUMIFS('Additions (monthly)'!$E$2:$E$106,'Additions (monthly)'!$D$2:$D$106,BI$2,'Additions (monthly)'!$B$2:$B$106,"<="&$B5) -> 6.7
A6: 40269 | B6: 201004 | C6: =SUMIFS('Additions (monthly)'!$E$2:$E$106,'Additions (monthly)'!$B$2:$B$106,"<="&$B6) -> 243.22 | D6: =SUMIFS('Additions (monthly)'!$E$2:$E$106,'Additions (monthly)'!$D$2:$D$106,D$2,'Additions (monthly)'!$B$2:$B$106,"<="&$B6) -> 7.9 | E6: =SUMIFS('Additions (monthly)'!$E$2:$E$106,'Additions (monthly)'!$D$2:$D$106,E$2,'Additions (monthly)'!$B$2:$B$106,"<="&$B6) -> 8.4 | F6: =SUMIFS('Additions (monthly)'!$E$2:$E$106,'Additions (monthly)'!$D$2:$D$106,F$2,'Additions (monthly)'!$B$2:$B$106,"<="&$B6) -> 0 | G6: =SUMIFS('Additions (monthly)'!$E$2:$E$106,'Additions (monthly)'!$D$2:$D$106,G$2,'Additions (monthly)'!$B$2:$B$106,"<="&$B6) -> 0 | H6: =SUMIFS('Additions (monthly)'!$E$2:$E$106,'Additions (monthly)'!$D$2:$D$106,H$2,'Additions (monthly)'!$B$2:$B$106,"<="&$B6) -> 0 | I6: =SUMIFS('Additions (monthly)'!$E$2:$E$106,'Additions (monthly)'!$D$2:$D$106,I$2,'Additions (monthly)'!$B$2:$B$106,"<="&$B6) -> 0 | J6: =SUMIFS('Additions (monthly)'!$E$2:$E$106,'Additions (monthly)'!$D$2:$D$106,J$2,'Additions (monthly)'!$B$2:$B$106,"<="&$B6) -> 3.7 | K6: =SUMIFS('Additions (monthly)'!$E$2:$E$106,'Additions (monthly)'!$D$2:$D$106,K$2,'Additions (monthly)'!$B$2:$B$106,"<="&$B6) -> 0 | ... BI6: =SUMIFS('Additions (monthly)'!$E$2:$E$106,'Additions (monthly)'!$D$2:$D$106,BI$2,'Additions (monthly)'!$B$2:$B$106,"<="&$B6) -> 6.7
A7: 40299 | B7: 201005 | C7: =SUMIFS('Additions (monthly)'!$E$2:$E$106,'Additions (monthly)'!$B$2:$B$106,"<="&$B7) -> 243.22 | D7: =SUMIFS('Additions (monthly)'!$E$2:$E$106,'Additions (monthly)'!$D$2:$D$106,D$2,'Additions (monthly)'!$B$2:$B$106,"<="&$B7) -> 7.9 | E7: =SUMIFS('Additions (monthly)'!$E$2:$E$106,'Additions (monthly)'!$D$2:$D$106,E$2,'Additions (monthly)'!$B$2:$B$106,"<="&$B7) -> 8.4 | F7: =SUMIFS('Additions (monthly)'!$E$2:$E$106,'Additions (monthly)'!$D$2:$D$106,F$2,'Additions (monthly)'!$B$2:$B$106,"<="&$B7) -> 0 | G7: =SUMIFS('Additions (monthly)'!$E$2:$E$106,'Additions (monthly)'!$D$2:$D$106,G$2,'Additions (monthly)'!$B$2:$B$106,"<="&$B7) -> 0 | H7: =SUMIFS('Additions (monthly)'!$E$2:$E$106,'Additions (monthly)'!$D$2:$D$106,H$2,'Additions (monthly)'!$B$2:$B$106,"<="&$B7) -> 0 | I7: =SUMIFS('Additions (monthly)'!$E$2:$E$106,'Additions (monthly)'!$D$2:$D$106,I$2,'Additions (monthly)'!$B$2:$B$106,"<="&$B7) -> 0 | J7: =SUMIFS('Additions (monthly)'!$E$2:$E$106,'Additions (monthly)'!$D$2:$D$106,J$2,'Additions (monthly)'!$B$2:$B$106,"<="&$B7) -> 3.7 | K7: =SUMIFS('Additions (monthly)'!$E$2:$E$106,'Additions (monthly)'!$D$2:$D$106,K$2,'Additions (monthly)'!$B$2:$B$106,"<="&$B7) -> 0 | ... BI7: =SUMIFS('Additions (monthly)'!$E$2:$E$106,'Additions (monthly)'!$D$2:$D$106,BI$2,'Additions (monthly)'!$B$2:$B$106,"<="&$B7) -> 6.7
A8: 40330 | B8: 201006 | C8: =SUMIFS('Additions (monthly)'!$E$2:$E$106,'Additions (monthly)'!$B$2:$B$106,"<="&$B8) -> 247.67 | D8: =SUMIFS('Additions (monthly)'!$E$2:$E$106,'Additions (monthly)'!$D$2:$D$106,D$2,'Additions (monthly)'!$B$2:$B$106,"<="&$B8) -> 7.9 | E8: =SUMIFS('Additions (monthly)'!$E$2:$E$106,'Additions (monthly)'!$D$2:$D$106,E$2,'Additions (monthly)'!$B$2:$B$106,"<="&$B8) -> 8.4 | F8: =SUMIFS('Additions (monthly)'!$E$2:$E$106,'Additions (monthly)'!$D$2:$D$106,F$2,'Additions (monthly)'!$B$2:$B$106,"<="&$B8) -> 0 | G8: =SUMIFS('Additions (monthly)'!$E$2:$E$106,'Additions (monthly)'!$D$2:$D$106,G$2,'Additions (monthly)'!$B$2:$B$106,"<="&$B8) -> 0 | H8: =SUMIFS('Additions (monthly)'!$E$2:$E$106,'Additions (monthly)'!$D$2:$D$106,H$2,'Additions (monthly)'!$B$2:$B$106,"<="&$B8) -> 0 | I8: =SUMIFS('Additions (monthly)'!$E$2:$E$106,'Additions (monthly)'!$D$2:$D$106,I$2,'Additions (monthly)'!$B$2:$B$106,"<="&$B8) -> 0 | J8: =SUMIFS('Additions (monthly)'!$E$2:$E$106,'Additions (monthly)'!$D$2:$D$106,J$2,'Additions (monthly)'!$B$2:$B$106,"<="&$B8) -> 3.7 | K8: =SUMIFS('Additions (monthly)'!$E$2:$E$106,'Additions (monthly)'!$D$2:$D$106,K$2,'Additions (monthly)'!$B$2:$B$106,"<="&$B8) -> 0 | ... BI8: =SUMIFS('Additions (monthly)'!$E$2:$E$106,'Additions (monthly)'!$D$2:$D$106,BI$2,'Additions (monthly)'!$B$2:$B$106,"<="&$B8) -> 6.7
A9: 40360 | B9: 201007 | C9: =SUMIFS('Additions (monthly)'!$E$2:$E$106,'Additions (monthly)'!$B$2:$B$106,"<="&$B9) -> 247.67 | D9: =SUMIFS('Additions (monthly)'!$E$2:$E$106,'Additions (monthly)'!$D$2:$D$106,D$2,'Additions (monthly)'!$B$2:$B$106,"<="&$B9) -> 7.9 | E9: =SUMIFS('Additions (monthly)'!$E$2:$E$106,'Additions (monthly)'!$D$2:$D$106,E$2,'Additions (monthly)'!$B$2:$B$106,"<="&$B9) -> 8.4 | F9: =SUMIFS('Additions (monthly)'!$E$2:$E$106,'Additions (monthly)'!$D$2:$D$106,F$2,'Additions (monthly)'!$B$2:$B$106,"<="&$B9) -> 0 | G9: =SUMIFS('Additions (monthly)'!$E$2:$E$106,'Additions (monthly)'!$D$2:$D$106,G$2,'Additions (monthly)'!$B$2:$B$106,"<="&$B9) -> 0 | H9: =SUMIFS('Additions (monthly)'!$E$2:$E$106,'Additions (monthly)'!$D$2:$D$106,H$2,'Additions (monthly)'!$B$2:$B$106,"<="&$B9) -> 0 | I9: =SUMIFS('Additions (monthly)'!$E$2:$E$106,'Additions (monthly)'!$D$2:$D$106,I$2,'Additions (monthly)'!$B$2:$B$106,"<="&$B9) -> 0 | J9: =SUMIFS('Additions (monthly)'!$E$2:$E$106,'Additions (monthly)'!$D$2:$D$106,J$2,'Additions (monthly)'!$B$2:$B$106,"<="&$B9) -> 3.7 | K9: =SUMIFS('Additions (monthly)'!$E$2:$E$106,'Additions (monthly)'!$D$2:$D$106,K$2,'Additions (monthly)'!$B$2:$B$106,"<="&$B9) -> 0 | ... BI9: =SUMIFS('Additions (monthly)'!$E$2:$E$106,'Additions (monthly)'!$D$2:$D$106,BI$2,'Additions (monthly)'!$B$2:$B$106,"<="&$B9) -> 6.7
A10: 40391 | B10: 201008 | C10: =SUMIFS('Additions (monthly)'!$E$2:$E$106,'Additions (monthly)'!$B$2:$B$106,"<="&$B10) -> 247.67 | D10: =SUMIFS('Additions (monthly)'!$E$2:$E$106,'Additions (monthly)'!$D$2:$D$106,D$2,'Additions (monthly)'!$B$2:$B$106,"<="&$B10) -> 7.9 | E10: =SUMIFS('Additions (monthly)'!$E$2:$E$106,'Additions (monthly)'!$D$2:$D$106,E$2,'Additions (monthly)'!$B$2:$B$106,"<="&$B10) -> 8.4 | F10: =SUMIFS('Additions (monthly)'!$E$2:$E$106,'Additions (monthly)'!$D$2:$D$106,F$2,'Additions (monthly)'!$B$2:$B$106,"<="&$B10) -> 0 | G10: =SUMIFS('Additions (monthly)'!$E$2:$E$106,'Additions (monthly)'!$D$2:$D$106,G$2,'Additions (monthly)'!$B$2:$B$106,"<="&$B10) -> 0 | H10: =SUMIFS('Additions (monthly)'!$E$2:$E$106,'Additions (monthly)'!$D$2:$D$106,H$2,'Additions (monthly)'!$B$2:$B$106,"<="&$B10) -> 0 | I10: =SUMIFS('Additions (monthly)'!$E$2:$E$106,'Additions (monthly)'!$D$2:$D$106,I$2,'Additions (monthly)'!$B$2:$B$106,"<="&$B10) -> 0 | J10: =SUMIFS('Additions (monthly)'!$E$2:$E$106,'Additions (monthly)'!$D$2:$D$106,J$2,'Additions (monthly)'!$B$2:$B$106,"<="&$B10) -> 3.7 | K10: =SUMIFS('Additions (monthly)'!$E$2:$E$106,'Additions (monthly)'!$D$2:$D$106,K$2,'Additions (monthly)'!$B$2:$B$106,"<="&$B10) -> 0 | ... BI10: =SUMIFS('Additions (monthly)'!$E$2:$E$106,'Additions (monthly)'!$D$2:$D$106,BI$2,'Additions (monthly)'!$B$2:$B$106,"<="&$B10) -> 6.7
A11: 40422 | B11: 201009 | C11: =SUMIFS('Additions (monthly)'!$E$2:$E$106,'Additions (monthly)'!$B$2:$B$106,"<="&$B11) -> 247.67 | D11: =SUMIFS('Additions (monthly)'!$E$2:$E$106,'Additions (monthly)'!$D$2:$D$106,D$2,'Additions (monthly)'!$B$2:$B$106,"<="&$B11) -> 7.9 | E11: =SUMIFS('Additions (monthly)'!$E$2:$E$106,'Additions (monthly)'!$D$2:$D$106,E$2,'Additions (monthly)'!$B$2:$B$106,"<="&$B11) -> 8.4 | F11: =SUMIFS('Additions (monthly)'!$E$2:$E$106,'Additions (monthly)'!$D$2:$D$106,F$2,'Additions (monthly)'!$B$2:$B$106,"<="&$B11) -> 0 | G11: =SUMIFS('Additions (monthly)'!$E$2:$E$106,'Additions (monthly)'!$D$2:$D$106,G$2,'Additions (monthly)'!$B$2:$B$106,"<="&$B11) -> 0 | H11: =SUMIFS('Additions (monthly)'!$E$2:$E$106,'Additions (monthly)'!$D$2:$D$106,H$2,'Additions (monthly)'!$B$2:$B$106,"<="&$B11) -> 0 | I11: =SUMIFS('Additions (monthly)'!$E$2:$E$106,'Additions (monthly)'!$D$2:$D$106,I$2,'Additions (monthly)'!$B$2:$B$106,"<="&$B11) -> 0 | J11: =SUMIFS('Additions (monthly)'!$E$2:$E$106,'Additions (monthly)'!$D$2:$D$106,J$2,'Additions (monthly)'!$B$2:$B$106,"<="&$B11) -> 3.7 | K11: =SUMIFS('Additions (monthly)'!$E$2:$E$106,'Additions (monthly)'!$D$2:$D$106,K$2,'Additions (monthly)'!$B$2:$B$106,"<="&$B11) -> 0 | ... BI11: =SUMIFS('Additions (monthly)'!$E$2:$E$106,'Additions (monthly)'!$D$2:$D$106,BI$2,'Additions (monthly)'!$B$2:$B$106,"<="&$B11) -> 6.7
A12: 40452 | B12: 201010 | C12: =SUMIFS('Additions (monthly)'!$E$2:$E$106,'Additions (monthly)'!$B$2:$B$106,"<="&$B12) -> 247.67 | D12: =SUMIFS('Additions (monthly)'!$E$2:$E$106,'Additions (monthly)'!$D$2:$D$106,D$2,'Additions (monthly)'!$B$2:$B$106,"<="&$B12) -> 7.9 | E12: =SUMIFS('Additions (monthly)'!$E$2:$E$106,'Additions (monthly)'!$D$2:$D$106,E$2,'Additions (monthly)'!$B$2:$B$106,"<="&$B12) -> 8.4 | F12: =SUMIFS('Additions (monthly)'!$E$2:$E$106,'Additions (monthly)'!$D$2:$D$106,F$2,'Additions (monthly)'!$B$2:$B$106,"<="&$B12) -> 0 | G12: =SUMIFS('Additions (monthly)'!$E$2:$E$106,'Additions (monthly)'!$D$2:$D$106,G$2,'Additions (monthly)'!$B$2:$B$106,"<="&$B12) -> 0 | H12: =SUMIFS('Additions (monthly)'!$E$2:$E$106,'Additions (monthly)'!$D$2:$D$106,H$2,'Additions (monthly)'!$B$2:$B$106,"<="&$B12) -> 0 | I12: =SUMIFS('Additions (monthly)'!$E$2:$E$106,'Additions (monthly)'!$D$2:$D$106,I$2,'Additions (monthly)'!$B$2:$B$106,"<="&$B12) -> 0 | J12: =SUMIFS('Additions (monthly)'!$E$2:$E$106,'Additions (monthly)'!$D$2:$D$106,J$2,'Additions (monthly)'!$B$2:$B$106,"<="&$B12) -> 3.7 | K12: =SUMIFS('Additions (monthly)'!$E$2:$E$106,'Additions (monthly)'!$D$2:$D$106,K$2,'Additions (monthly)'!$B$2:$B$106,"<="&$B12) -> 0 | ... BI12: =SUMIFS('Additions (monthly)'!$E$2:$E$106,'Additions (monthly)'!$D$2:$D$106,BI$2,'Additions (monthly)'!$B$2:$B$106,"<="&$B12) -> 6.7
A13: 40483 | B13: 201011 | C13: =SUMIFS('Additions (monthly)'!$E$2:$E$106,'Additions (monthly)'!$B$2:$B$106,"<="&$B13) -> 255.77 | D13: =SUMIFS('Additions (monthly)'!$E$2:$E$106,'Additions (monthly)'!$D$2:$D$106,D$2,'Additions (monthly)'!$B$2:$B$106,"<="&$B13) -> 7.9 | E13: =SUMIFS('Additions (monthly)'!$E$2:$E$106,'Additions (monthly)'!$D$2:$D$106,E$2,'Additions (monthly)'!$B$2:$B$106,"<="&$B13) -> 8.4 | F13: =SUMIFS('Additions (monthly)'!$E$2:$E$106,'Additions (monthly)'!$D$2:$D$106,F$2,'Additions (monthly)'!$B$2:$B$106,"<="&$B13) -> 0 | G13: =SUMIFS('Additions (monthly)'!$E$2:$E$106,'Additions (monthly)'!$D$2:$D$106,G$2,'Additions (monthly)'!$B$2:$B$106,"<="&$B13) -> 0 | H13: =SUMIFS('Additions (monthly)'!$E$2:$E$106,'Additions (monthly)'!$D$2:$D$106,H$2,'Additions (monthly)'!$B$2:$B$106,"<="&$B13) -> 0 | I13: =SUMIFS('Additions (monthly)'!$E$2:$E$106,'Additions (monthly)'!$D$2:$D$106,I$2,'Additions (monthly)'!$B$2:$B$106,"<="&$B13) -> 0 | J13: =SUMIFS('Additions (monthly)'!$E$2:$E$106,'Additions (monthly)'!$D$2:$D$106,J$2,'Additions (monthly)'!$B$2:$B$106,"<="&$B13) -> 3.7 | K13: =SUMIFS('Additions (monthly)'!$E$2:$E$106,'Additions (monthly)'!$D$2:$D$106,K$2,'Additions (monthly)'!$B$2:$B$106,"<="&$B13) -> 0 | ... BI13: =SUMIFS('Additions (monthly)'!$E$2:$E$106,'Additions (monthly)'!$D$2:$D$106,BI$2,'Additions (monthly)'!$B$2:$B$106,"<="&$B13) -> 6.7
A14: 40513 | B14: 201012 | C14: =SUMIFS('Additions (monthly)'!$E$2:$E$106,'Additions (monthly)'!$B$2:$B$106,"<="&$B14) -> 255.77 | D14: =SUMIFS('Additions (monthly)'!$E$2:$E$106,'Additions (monthly)'!$D$2:$D$106,D$2,'Additions (monthly)'!$B$2:$B$106,"<="&$B14) -> 7.9 | E14: =SUMIFS('Additions (monthly)'!$E$2:$E$106,'Additions (monthly)'!$D$2:$D$106,E$2,'Additions (monthly)'!$B$2:$B$106,"<="&$B14) -> 8.4 | F14: =SUMIFS('Additions (monthly)'!$E$2:$E$106,'Additions (monthly)'!$D$2:$D$106,F$2,'Additions (monthly)'!$B$2:$B$106,"<="&$B14) -> 0 | G14: =SUMIFS('Additions (monthly)'!$E$2:$E$106,'Additions (monthly)'!$D$2:$D$106,G$2,'Additions (monthly)'!$B$2:$B$106,"<="&$B14) -> 0 | H14: =SUMIFS('Additions (monthly)'!$E$2:$E$106,'Additions (monthly)'!$D$2:$D$106,H$2,'Additions (monthly)'!$B$2:$B$106,"<="&$B14) -> 0 | I14: =SUMIFS('Additions (monthly)'!$E$2:$E$106,'Additions (monthly)'!$D$2:$D$106,I$2,'Additions (monthly)'!$B$2:$B$106,"<="&$B14) -> 0 | J14: =SUMIFS('Additions (monthly)'!$E$2:$E$106,'Additions (monthly)'!$D$2:$D$106,J$2,'Additions (monthly)'!$B$2:$B$106,"<="&$B14) -> 3.7 | K14: =SUMIFS('Additions (monthly)'!$E$2:$E$106,'Additions (monthly)'!$D$2:$D$106,K$2,'Additions (monthly)'!$B$2:$B$106,"<="&$B14) -> 0 | ... BI14: =SUMIFS('Additions (monthly)'!$E$2:$E$106,'Additions (monthly)'!$D$2:$D$106,BI$2,'Additions (monthly)'!$B$2:$B$106,"<="&$B14) -> 6.7
... A206: 46357 | B206: 202612 | C206: =SUMIFS('Additions (monthly)'!$E$2:$E$106,'Additions (monthly)'!$B$2:$B$106,"<="&$B206) -> 565.07 | D206: =SUMIFS('Additions (monthly)'!$E$2:$E$106,'Additions (monthly)'!$D$2:$D$106,D$2,'Additions (monthly)'!$B$2:$B$106,"<="&$B206) -> 7.9 | E206: =SUMIFS('Additions (monthly)'!$E$2:$E$106,'Additions (monthly)'!$D$2:$D$106,E$2,'Additions (monthly)'!$B$2:$B$106,"<="&$B206) -> 8.4 | F206: =SUMIFS('Additions (monthly)'!$E$2:$E$106,'Additions (monthly)'!$D$2:$D$106,F$2,'Additions (monthly)'!$B$2:$B$106,"<="&$B206) -> 4.7 | G206: =SUMIFS('Additions (monthly)'!$E$2:$E$106,'Additions (monthly)'!$D$2:$D$106,G$2,'Additions (monthly)'!$B$2:$B$106,"<="&$B206) -> 4.5 | H206: =SUMIFS('Additions (monthly)'!$E$2:$E$106,'Additions (monthly)'!$D$2:$D$106,H$2,'Additions (monthly)'!$B$2:$B$106,"<="&$B206) -> 5.2 | I206: =SUMIFS('Additions (monthly)'!$E$2:$E$106,'Additions (monthly)'!$D$2:$D$106,I$2,'Additions (monthly)'!$B$2:$B$106,"<="&$B206) -> 9 | J206: =SUMIFS('Additions (monthly)'!$E$2:$E$106,'Additions (monthly)'!$D$2:$D$106,J$2,'Additions (monthly)'!$B$2:$B$106,"<="&$B206) -> 3.7 | K206: =SUMIFS('Additions (monthly)'!$E$2:$E$106,'Additions (monthly)'!$D$2:$D$106,K$2,'Additions (monthly)'!$B$2:$B$106,"<="&$B206) -> 7.8 | ... BI206: =SUMIFS('Additions (monthly)'!$E$2:$E$106,'Additions (monthly)'!$D$2:$D$106,BI$2,'Additions (monthly)'!$B$2:$B$106,"<="&$B206) -> 6.7
A208: MONTH-BY-MONTH LNG EXPORT (LIQUEFACTION) NAMEPLATE CAPACITY, Mtpa, Jan 2010 – Dec 2026. Each cell = terminal nameplate operational as of month-end (cumulative). Global Total & terminal columns are live SUMIFS over "Additions (monthly)".
A209: 2026 ADDITIONS (from IEA Global LNG Capacity Tracker + operator news): Golden Pass T1 (Mar) & T2 (Oct), LNG Canada T2, Corpus Christi Stage 3 T5-T7, ECA Mexico (Jun), Congo Nguya FLNG (Feb), Qatar NFE T1 (~Sep), Pluto T2/Scarborough (~Nov). Global total: 524.55 (Dec 2025) → 565.07 Mtpa (Dec 2026).
A210: IEA GAPS: some H1-2026 startups the IEA tracker had not yet logged are included from news (e.g., Congo Nguya FLNG, Golden Pass T1, ECA). H2-2026 items (NFE, Golden Pass T2, Pluto T2, Corpus T7) are expected/forecast and carry slippage risk. Plaquemines is already at full nameplate (19.44) from 2025 — its 2026 "ramp" is output, not nameplate, so not re-added.
A211: Nameplate only — not actual output. See "Monthly outages (Mtpa)" for estimated capacity offline; net available = capacity − outages.

Sheet Commissioning schedule
A1: Commissioning Month | B1: Month (date) | C1: Country | D1: Terminal | E1: Trains added | F1: Capacity added (Mtpa) | G1: Cumulative capacity (Mtpa) | H1: IGU start year | I1: Basis | J1: Conf. | K1: Notes | L1: Source
A2: ≤2009 (baseline) | B2: 40148 | C2: — | D2: Pre-2010 baseline — all plants online before 2010 (55 trains) | E2: 55 | F2: 239.4 | G2: 239.4 | H2: ≤2009 | I2: operating | J2: — | K2: Sum of all trains with start year ≤2009; already online at Jan 2010 | L2: IGU WLR 2026 App.1
A3: 2010-01 | B3: 40179 | C3: China | D3: Inland facilities | E3: 1 | F3: 3.87 | G3: =G2+F3 -> 243.27 | H3: 2010 | I3: baseline | J3: High | K3: Aggregate pre-2010 small-scale inland capacity; treated as online at Jan 2010
A4: 2010-06 | B4: 40330 | C4: Peru | D4: Peru LNG | E4: 1 | F4: 4.45 | G4: =G3+F4 -> 247.72 | H4: 2010 | I4: first-cargo | J4: High | K4: First cargo 22 Jun 2010 | L4: https://www.prnewswire.com/news-releases/peru-lng-inaugurates-the-first-natural-gas-liquefaction-lng-plant-in-south-america-96065044.html
A5: 2010-11 | B5: 40483 | C5: Norway | D5: Nordic LNG | E5: 1 | F5: 0.3 | G5: =G4+F5 -> 248.02 | H5: 2010 | I5: first-LNG | J5: Low | K5: Official opening Oct 2011; commissioning ~late 2010 | L5: https://www.gem.wiki/Risavika_LNG_Terminal
A6: 2010-11 | B6: 40483 | C6: Qatar | D6: QatarGas LNG | E6: 1 | F6: 7.8 | G6: =G5+F6 -> 255.82 | H6: 2010 | I6: first-LNG | J6: High | K6: First LNG 1 Nov 2010 | L6: https://www.offshore-energy.biz/qatargas-train-6-produces-first-lng/
A7: 2011-02 | B7: 40575 | C7: Qatar | D7: QatarGas LNG | E7: 1 | F7: 7.8 | G7: =G6+F7 -> 263.62 | H7: 2011 | I7: first-LNG | J7: Med | K7: Operations announced 10 Feb 2011 | L7: https://www.ogj.com/pipelines-transportation/lng/article/17267015/qatargas-4s-train-7-begins-operations
A8: 2012-04 | B8: 41000 | C8: Australia | D8: Pluto LNG | E8: 1 | F8: 4.9 | G8: =G7+F8 -> 268.52 | H8: 2012 | I8: first-LNG | J8: High | K8: Woodside start 30 Apr 2012; first cargo May 2012 | L8: https://www.bloomberg.com/news/articles/2012-04-30/woodside-starts-lng-production-at-pluto-development-in-australia
A9: 2013-03 | B9: 41334 | C9: Algeria | D9: Skikda GL1K | E9: 1 | F9: 4.5 | G9: =G8+F9 -> 273.02 | H9: 2013 | I9: first-LNG | J9: Low | K9: Rebuilt train after 2004 explosion; ~2013 | L9: https://www.gem.wiki/Sonatrach_Skikda_LNG_Terminal
A10: 2013-06 | B10: 41426 | C10: Angola | D10: Angola LNG | E10: 1 | F10: 5.2 | G10: =G9+F10 -> 278.22 | H10: 2013 | I10: first-cargo | J10: High | K10: First cargo 16 Jun 2013 | L10: https://www.prnewswire.com/news-releases/angola-lng-ships-first-cargo-211725271.html
A11: 2014-04 | B11: 41730 | C11: Papua New Guinea | D11: PNG LNG | E11: 2 | F11: 6.9 | G11: =G10+F11 -> 285.12 | H11: 2014 | I11: first-LNG | J11: High | K11: Start-up 28 Apr 2014; first cargo May 2014 | L11: https://investor.exxonmobil.com/company-information/press-releases/detail/564/exxonmobil-starts-production-ahead-of-schedule-at-png-lng
A12: 2014-11 | B12: 41944 | C12: Algeria | D12: Arzew GL3Z (Gassi Touil) | E12: 1 | F12: 4.7 | G12: =G11+F12 -> 289.82 | H12: 2014 | I12: first-LNG | J12: Med | K12: Project completed Nov 2014 | L12: https://www.gem.wiki/Arzew-Bethioua_LNG_Terminal
A13: 2014-12 | B13: 41974 | C13: Australia | D13: Queensland Curtis LNG | E13: 2 | F13: 8.5 | G13: =G12+F13 -> 298.32 | H13: 2015 | I13: first-LNG | J13: High | K13: First LNG Dec 2014 (IGU lists 2015) | L13: https://www.oedigital.com/news/452553-qclng-begins-operations
A14: 2015-06 | B14: 42156 | C14: Indonesia | D14: Donggi- Senoro LNG | E14: 1 | F14: 2 | G14: =G13+F14 -> 300.32 | H14: 2015 | I14: first-LNG | J14: Med | K14: Commissioning ~Jun; first cargo Aug 2015 | L14: https://www.gem.wiki/Donggi-Senoro_LNG_Terminal
A15: 2015-09 | B15: 42248 | C15: Australia | D15: GLNG | E15: 1 | F15: 3.9 | G15: =G14+F15 -> 304.22 | H15: 2015 | I15: first-LNG | J15: High | K15: First LNG 24 Sep 2015 | L15: https://www.santos.com/news/2015-glng-starts-lng-production-on-schedule/
... A54: 2025-06 | B54: 45809 | C54: United States | D54: Plaquemines LNG | E54: 28 | F54: 15.12 | G54: =G53+F54 -> 524.6 | H54: 2025 | I54: commercial-start | J54: Low | K54: Representative month; multiple modular blocks online through 2025 | L54: https://www.eia.gov/todayinenergy/detail.php?id=64224
A56: HOW TO USE: rows are sorted by commissioning month. "Capacity added" is the nameplate step; "Cumulative capacity" forward-fills to give the export-capacity level. For a full month-by-month series, carry each cumulative value forward across the months until the next row.
A57: ORANGE ROWS: the researched first-LNG month falls in an EARLIER year than IGU's assigned "start year" (IGU tends to date plants to substantial-completion / commercial operations, not first commissioning LNG). Use the "IGU start year" column instead if you prefer to align with the annual file. This choice only shifts capacity by 1–2 months around a year boundary.
A58: BASIS: "first-LNG" = first commissioning production (preferred); "first-cargo" = first export shipment (first-LNG slightly earlier); "commercial-start" = declared commercial operations (first-LNG earlier). Confidence flags source certainty on the exact month.
A59: MODULAR PROJECTS (Calcasieu Pass, Plaquemines, Elba Island) ramp capacity over many months, not in a single step. The month shown is first-LNG; the full nameplate is reached gradually. For a precise monthly series these should be spread across their ramp — happy to model that.
A60: Cumulative reaches 524.55 Mtpa (end-2025), matching IGU WLR 2026 and GIIGNL (~524 Mtpa). Source: IGU World LNG Report 2026, Appendix 1, plus per-event commissioning sources listed per row.

Sheet Train detail
A1: RefNo | B1: Country | C1: Terminal | D1: Train | E1: Technology | F1: Start Year | G1: Capacity (Mtpa) | H1: Ownership | I1: Note
A2: 1 | B2: Brunei | C2: Brunei LNG | D2: Brunei LNG T1-T2 | E2: AP-C3MR | F2: 1972 | G2: 2.88 | H2: Shell* (25%); Brunei Government (50%); Mitsubishi Corp (25%)
A3: 1 | B3: Brunei | C3: Brunei LNG | D3: Brunei LNG T3-T4 | E3: AP-C3MR | F3: 1973 | G3: 2.88 | H3: Shell* (25%); Brunei Government (50%); Mitsubishi Corp (25%)
A4: 1 | B4: Brunei | C4: Brunei LNG | D4: Brunei LNG T5 | E4: AP-C3MR | F4: 1974 | G4: 1.44 | H4: Shell* (25%); Brunei Government (50%); Mitsubishi Corp (25%)
A5: 2 | B5: UAE | C5: Adgas LNG | D5: Adgas LNG T1 | E5: AP-C3MR | F5: 1977 | G5: 1.15 | H5: ADNOC LNG* (0%); ADNOC (70%); Mitsui (15%); BP (10%); TotalEnergies (5%)
A6: 2 | B6: UAE | C6: Adgas LNG | D6: Adgas LNG T2 | E6: AP-C3MR | F6: 1977 | G6: 1.15 | H6: ADNOC LNG* (0%); ADNOC (70%); Mitsui (15%); BP (10%); TotalEnergies (5%)
A7: 2 | B7: UAE | C7: Adgas LNG | D7: Adgas LNG T3 | E7: AP-C3MR | F7: 1994 | G7: 3 | H7: ADNOC LNG* (0%); ADNOC (70%); Mitsui (15%); BP (10%); TotalEnergies (5%)
A8: 3 | B8: Algeria | C8: Arzew GL1Z | D8: Arzew GL1Z T1-T6 | E8: AP-C3MR | F8: 1978 | G8: 7.9 | H8: Sonatrach* (100%)
A9: 4 | B9: Algeria | C9: Arzew GL2Z | D9: Arzew GL2Z T1-T6 | E9: AP-C3MR | F9: 1981 | G9: 8.4 | H9: Sonatrach* (100%)
A10: 5 | B10: Malaysia | C10: MLNG | D10: MLNG Satu T1-T3 | E10: AP-C3MR | F10: 1982 | G10: 8.4 | H10: Petronas* (90%); Mitsubishi Corp (5%); Sarawak State (5%)
A11: 5 | B11: Malaysia | C11: MLNG | D11: MLNG Dua T4-T6 | E11: AP-C3MR | F11: 1995 | G11: 9.6 | H11: Petronas* (80%); Mitsubishi Corp (10%); Sarawak State (10%)
A12: 5 | B12: Malaysia | C12: MLNG | D12: MLNG Tiga T7-T8 | E12: AP-C3MR | F12: 2003 | G12: 7.7 | H12: Petronas* (60%); Sarawak State (25%); JX Nippon Oil and Gas (10%); Mitsubishi Corp (5%)
A13: 5 | B13: Malaysia | C13: MLNG | D13: MLNG T9 | E13: AP-C3MR/ SplitMR | F13: 2017 | G13: 3.6 | H13: Petronas* (80%); JX Nippon Oil and Gas (10%); Sarawak State (10%)
... A180: 53 | B180: Canada | C180: LNG Canada | D180: LNG Canada T1 | E180: Shell DMR | F180: 2025 | G180: 7 | H180: Shell* (40%); Petronas (20%); MidOcean Energy (5%); Mitsubishi Corp (15%); PetroChina (15%); Korea Gas (5%);
A181: 54 | B181: China | C181: Inland facilities | D181: - | E181: - | F181: 2010 | G181: 3.87 | H181: - | I181: Start year not given in source; set to 2010 for inclusion

Sheet Terminal x Year
A1: Country | B1: Terminal | C1: First Online | D1: Nameplate end-2025 (Mtpa) | E1: 2010 | F1: 2011 | G1: 2012 | H1: 2013 | I1: 2014 | J1: 2015 | K1: 2016 | L1: 2017 | M1: 2018 | N1: 2019 | O1: 2020 | P1: 2021 | Q1: 2022 | R1: 2023 | S1: 2024 | T1: 2025
A2: Brunei | B2: Brunei LNG | C2: 1972 | D2: =SUMIFS('Train detail'!$G$2:$G$181,'Train detail'!$B$2:$B$181,$A2,'Train detail'!$C$2:$C$181,$B2) -> 7.2 | E2: =SUMIFS('Train detail'!$G$2:$G$181,'Train detail'!$B$2:$B$181,$A2,'Train detail'!$C$2:$C$181,$B2,'Train detail'!$F$2:$F$181,"<="&2010) -> 7.2 | F2: =SUMIFS('Train detail'!$G$2:$G$181,'Train detail'!$B$2:$B$181,$A2,'Train detail'!$C$2:$C$181,$B2,'Train detail'!$F$2:$F$181,"<="&2011) -> 7.2 | G2: =SUMIFS('Train detail'!$G$2:$G$181,'Train detail'!$B$2:$B$181,$A2,'Train detail'!$C$2:$C$181,$B2,'Train detail'!$F$2:$F$181,"<="&2012) -> 7.2 | H2: =SUMIFS('Train detail'!$G$2:$G$181,'Train detail'!$B$2:$B$181,$A2,'Train detail'!$C$2:$C$181,$B2,'Train detail'!$F$2:$F$181,"<="&2013) -> 7.2 | I2: =SUMIFS('Train detail'!$G$2:$G$181,'Train detail'!$B$2:$B$181,$A2,'Train detail'!$C$2:$C$181,$B2,'Train detail'!$F$2:$F$181,"<="&2014) -> 7.2 | J2: =SUMIFS('Train detail'!$G$2:$G$181,'Train detail'!$B$2:$B$181,$A2,'Train detail'!$C$2:$C$181,$B2,'Train detail'!$F$2:$F$181,"<="&2015) -> 7.2 | K2: =SUMIFS('Train detail'!$G$2:$G$181,'Train detail'!$B$2:$B$181,$A2,'Train detail'!$C$2:$C$181,$B2,'Train detail'!$F$2:$F$181,"<="&2016) -> 7.2 | L2: =SUMIFS('Train detail'!$G$2:$G$181,'Train detail'!$B$2:$B$181,$A2,'Train detail'!$C$2:$C$181,$B2,'Train detail'!$F$2:$F$181,"<="&2017) -> 7.2 | M2: =SUMIFS('Train detail'!$G$2:$G$181,'Train detail'!$B$2:$B$181,$A2,'Train detail'!$C$2:$C$181,$B2,'Train detail'!$F$2:$F$181,"<="&2018) -> 7.2 | N2: =SUMIFS('Train detail'!$G$2:$G$181,'Train detail'!$B$2:$B$181,$A2,'Train detail'!$C$2:$C$181,$B2,'Train detail'!$F$2:$F$181,"<="&2019) -> 7.2 | O2: =SUMIFS('Train detail'!$G$2:$G$181,'Train detail'!$B$2:$B$181,$A2,'Train detail'!$C$2:$C$181,$B2,'Train detail'!$F$2:$F$181,"<="&2020) -> 7.2 | P2: =SUMIFS('Train detail'!$G$2:$G$181,'Train detail'!$B$2:$B$181,$A2,'Train detail'!$C$2:$C$181,$B2,'Train detail'!$F$2:$F$181,"<="&2021) -> 7.2 | Q2: =SUMIFS('Train detail'!$G$2:$G$181,'Train detail'!$B$2:$B$181,$A2,'Train detail'!$C$2:$C$181,$B2,'Train detail'!$F$2:$F$181,"<="&2022) -> 7.2 | R2: =SUMIFS('Train detail'!$G$2:$G$181,'Train detail'!$B$2:$B$181,$A2,'Train detail'!$C$2:$C$181,$B2,'Train detail'!$F$2:$F$181,"<="&2023) -> 7.2 | S2: =SUMIFS('Train detail'!$G$2:$G$181,'Train detail'!$B$2:$B$181,$A2,'Train detail'!$C$2:$C$181,$B2,'Train detail'!$F$2:$F$181,"<="&2024) -> 7.2 | T2: =SUMIFS('Train detail'!$G$2:$G$181,'Train detail'!$B$2:$B$181,$A2,'Train detail'!$C$2:$C$181,$B2,'Train detail'!$F$2:$F$181,"<="&2025) -> 7.2
A3: UAE | B3: Adgas LNG | C3: 1977 | D3: =SUMIFS('Train detail'!$G$2:$G$181,'Train detail'!$B$2:$B$181,$A3,'Train detail'!$C$2:$C$181,$B3) -> 5.3 | E3: =SUMIFS('Train detail'!$G$2:$G$181,'Train detail'!$B$2:$B$181,$A3,'Train detail'!$C$2:$C$181,$B3,'Train detail'!$F$2:$F$181,"<="&2010) -> 5.3 | F3: =SUMIFS('Train detail'!$G$2:$G$181,'Train detail'!$B$2:$B$181,$A3,'Train detail'!$C$2:$C$181,$B3,'Train detail'!$F$2:$F$181,"<="&2011) -> 5.3 | G3: =SUMIFS('Train detail'!$G$2:$G$181,'Train detail'!$B$2:$B$181,$A3,'Train detail'!$C$2:$C$181,$B3,'Train detail'!$F$2:$F$181,"<="&2012) -> 5.3 | H3: =SUMIFS('Train detail'!$G$2:$G$181,'Train detail'!$B$2:$B$181,$A3,'Train detail'!$C$2:$C$181,$B3,'Train detail'!$F$2:$F$181,"<="&2013) -> 5.3 | I3: =SUMIFS('Train detail'!$G$2:$G$181,'Train detail'!$B$2:$B$181,$A3,'Train detail'!$C$2:$C$181,$B3,'Train detail'!$F$2:$F$181,"<="&2014) -> 5.3 | J3: =SUMIFS('Train detail'!$G$2:$G$181,'Train detail'!$B$2:$B$181,$A3,'Train detail'!$C$2:$C$181,$B3,'Train detail'!$F$2:$F$181,"<="&2015) -> 5.3 | K3: =SUMIFS('Train detail'!$G$2:$G$181,'Train detail'!$B$2:$B$181,$A3,'Train detail'!$C$2:$C$181,$B3,'Train detail'!$F$2:$F$181,"<="&2016) -> 5.3 | L3: =SUMIFS('Train detail'!$G$2:$G$181,'Train detail'!$B$2:$B$181,$A3,'Train detail'!$C$2:$C$181,$B3,'Train detail'!$F$2:$F$181,"<="&2017) -> 5.3 | M3: =SUMIFS('Train detail'!$G$2:$G$181,'Train detail'!$B$2:$B$181,$A3,'Train detail'!$C$2:$C$181,$B3,'Train detail'!$F$2:$F$181,"<="&2018) -> 5.3 | N3: =SUMIFS('Train detail'!$G$2:$G$181,'Train detail'!$B$2:$B$181,$A3,'Train detail'!$C$2:$C$181,$B3,'Train detail'!$F$2:$F$181,"<="&2019) -> 5.3 | O3: =SUMIFS('Train detail'!$G$2:$G$181,'Train detail'!$B$2:$B$181,$A3,'Train detail'!$C$2:$C$181,$B3,'Train detail'!$F$2:$F$181,"<="&2020) -> 5.3 | P3: =SUMIFS('Train detail'!$G$2:$G$181,'Train detail'!$B$2:$B$181,$A3,'Train detail'!$C$2:$C$181,$B3,'Train detail'!$F$2:$F$181,"<="&2021) -> 5.3 | Q3: =SUMIFS('Train detail'!$G$2:$G$181,'Train detail'!$B$2:$B$181,$A3,'Train detail'!$C$2:$C$181,$B3,'Train detail'!$F$2:$F$181,"<="&2022) -> 5.3 | R3: =SUMIFS('Train detail'!$G$2:$G$181,'Train detail'!$B$2:$B$181,$A3,'Train detail'!$C$2:$C$181,$B3,'Train detail'!$F$2:$F$181,"<="&2023) -> 5.3 | S3: =SUMIFS('Train detail'!$G$2:$G$181,'Train detail'!$B$2:$B$181,$A3,'Train detail'!$C$2:$C$181,$B3,'Train detail'!$F$2:$F$181,"<="&2024) -> 5.3 | T3: =SUMIFS('Train detail'!$G$2:$G$181,'Train detail'!$B$2:$B$181,$A3,'Train detail'!$C$2:$C$181,$B3,'Train detail'!$F$2:$F$181,"<="&2025) -> 5.3
A4: Algeria | B4: Arzew GL1Z | C4: 1978 | D4: =SUMIFS('Train detail'!$G$2:$G$181,'Train detail'!$B$2:$B$181,$A4,'Train detail'!$C$2:$C$181,$B4) -> 7.9 | E4: =SUMIFS('Train detail'!$G$2:$G$181,'Train detail'!$B$2:$B$181,$A4,'Train detail'!$C$2:$C$181,$B4,'Train detail'!$F$2:$F$181,"<="&2010) -> 7.9 | F4: =SUMIFS('Train detail'!$G$2:$G$181,'Train detail'!$B$2:$B$181,$A4,'Train detail'!$C$2:$C$181,$B4,'Train detail'!$F$2:$F$181,"<="&2011) -> 7.9 | G4: =SUMIFS('Train detail'!$G$2:$G$181,'Train detail'!$B$2:$B$181,$A4,'Train detail'!$C$2:$C$181,$B4,'Train detail'!$F$2:$F$181,"<="&2012) -> 7.9 | H4: =SUMIFS('Train detail'!$G$2:$G$181,'Train detail'!$B$2:$B$181,$A4,'Train detail'!$C$2:$C$181,$B4,'Train detail'!$F$2:$F$181,"<="&2013) -> 7.9 | I4: =SUMIFS('Train detail'!$G$2:$G$181,'Train detail'!$B$2:$B$181,$A4,'Train detail'!$C$2:$C$181,$B4,'Train detail'!$F$2:$F$181,"<="&2014) -> 7.9 | J4: =SUMIFS('Train detail'!$G$2:$G$181,'Train detail'!$B$2:$B$181,$A4,'Train detail'!$C$2:$C$181,$B4,'Train detail'!$F$2:$F$181,"<="&2015) -> 7.9 | K4: =SUMIFS('Train detail'!$G$2:$G$181,'Train detail'!$B$2:$B$181,$A4,'Train detail'!$C$2:$C$181,$B4,'Train detail'!$F$2:$F$181,"<="&2016) -> 7.9 | L4: =SUMIFS('Train detail'!$G$2:$G$181,'Train detail'!$B$2:$B$181,$A4,'Train detail'!$C$2:$C$181,$B4,'Train detail'!$F$2:$F$181,"<="&2017) -> 7.9 | M4: =SUMIFS('Train detail'!$G$2:$G$181,'Train detail'!$B$2:$B$181,$A4,'Train detail'!$C$2:$C$181,$B4,'Train detail'!$F$2:$F$181,"<="&2018) -> 7.9 | N4: =SUMIFS('Train detail'!$G$2:$G$181,'Train detail'!$B$2:$B$181,$A4,'Train detail'!$C$2:$C$181,$B4,'Train detail'!$F$2:$F$181,"<="&2019) -> 7.9 | O4: =SUMIFS('Train detail'!$G$2:$G$181,'Train detail'!$B$2:$B$181,$A4,'Train detail'!$C$2:$C$181,$B4,'Train detail'!$F$2:$F$181,"<="&2020) -> 7.9 | P4: =SUMIFS('Train detail'!$G$2:$G$181,'Train detail'!$B$2:$B$181,$A4,'Train detail'!$C$2:$C$181,$B4,'Train detail'!$F$2:$F$181,"<="&2021) -> 7.9 | Q4: =SUMIFS('Train detail'!$G$2:$G$181,'Train detail'!$B$2:$B$181,$A4,'Train detail'!$C$2:$C$181,$B4,'Train detail'!$F$2:$F$181,"<="&2022) -> 7.9 | R4: =SUMIFS('Train detail'!$G$2:$G$181,'Train detail'!$B$2:$B$181,$A4,'Train detail'!$C$2:$C$181,$B4,'Train detail'!$F$2:$F$181,"<="&2023) -> 7.9 | S4: =SUMIFS('Train detail'!$G$2:$G$181,'Train detail'!$B$2:$B$181,$A4,'Train detail'!$C$2:$C$181,$B4,'Train detail'!$F$2:$F$181,"<="&2024) -> 7.9 | T4: =SUMIFS('Train detail'!$G$2:$G$181,'Train detail'!$B$2:$B$181,$A4,'Train detail'!$C$2:$C$181,$B4,'Train detail'!$F$2:$F$181,"<="&2025) -> 7.9
A5: Algeria | B5: Arzew GL2Z | C5: 1981 | D5: =SUMIFS('Train detail'!$G$2:$G$181,'Train detail'!$B$2:$B$181,$A5,'Train detail'!$C$2:$C$181,$B5) -> 8.4 | E5: =SUMIFS('Train detail'!$G$2:$G$181,'Train detail'!$B$2:$B$181,$A5,'Train detail'!$C$2:$C$181,$B5,'Train detail'!$F$2:$F$181,"<="&2010) -> 8.4 | F5: =SUMIFS('Train detail'!$G$2:$G$181,'Train detail'!$B$2:$B$181,$A5,'Train detail'!$C$2:$C$181,$B5,'Train detail'!$F$2:$F$181,"<="&2011) -> 8.4 | G5: =SUMIFS('Train detail'!$G$2:$G$181,'Train detail'!$B$2:$B$181,$A5,'Train detail'!$C$2:$C$181,$B5,'Train detail'!$F$2:$F$181,"<="&2012) -> 8.4 | H5: =SUMIFS('Train detail'!$G$2:$G$181,'Train detail'!$B$2:$B$181,$A5,'Train detail'!$C$2:$C$181,$B5,'Train detail'!$F$2:$F$181,"<="&2013) -> 8.4 | I5: =SUMIFS('Train detail'!$G$2:$G$181,'Train detail'!$B$2:$B$181,$A5,'Train detail'!$C$2:$C$181,$B5,'Train detail'!$F$2:$F$181,"<="&2014) -> 8.4 | J5: =SUMIFS('Train detail'!$G$2:$G$181,'Train detail'!$B$2:$B$181,$A5,'Train detail'!$C$2:$C$181,$B5,'Train detail'!$F$2:$F$181,"<="&2015) -> 8.4 | K5: =SUMIFS('Train detail'!$G$2:$G$181,'Train detail'!$B$2:$B$181,$A5,'Train detail'!$C$2:$C$181,$B5,'Train detail'!$F$2:$F$181,"<="&2016) -> 8.4 | L5: =SUMIFS('Train detail'!$G$2:$G$181,'Train detail'!$B$2:$B$181,$A5,'Train detail'!$C$2:$C$181,$B5,'Train detail'!$F$2:$F$181,"<="&2017) -> 8.4 | M5: =SUMIFS('Train detail'!$G$2:$G$181,'Train detail'!$B$2:$B$181,$A5,'Train detail'!$C$2:$C$181,$B5,'Train detail'!$F$2:$F$181,"<="&2018) -> 8.4 | N5: =SUMIFS('Train detail'!$G$2:$G$181,'Train detail'!$B$2:$B$181,$A5,'Train detail'!$C$2:$C$181,$B5,'Train detail'!$F$2:$F$181,"<="&2019) -> 8.4 | O5: =SUMIFS('Train detail'!$G$2:$G$181,'Train detail'!$B$2:$B$181,$A5,'Train detail'!$C$2:$C$181,$B5,'Train detail'!$F$2:$F$181,"<="&2020) -> 8.4 | P5: =SUMIFS('Train detail'!$G$2:$G$181,'Train detail'!$B$2:$B$181,$A5,'Train detail'!$C$2:$C$181,$B5,'Train detail'!$F$2:$F$181,"<="&2021) -> 8.4 | Q5: =SUMIFS('Train detail'!$G$2:$G$181,'Train detail'!$B$2:$B$181,$A5,'Train detail'!$C$2:$C$181,$B5,'Train detail'!$F$2:$F$181,"<="&2022) -> 8.4 | R5: =SUMIFS('Train detail'!$G$2:$G$181,'Train detail'!$B$2:$B$181,$A5,'Train detail'!$C$2:$C$181,$B5,'Train detail'!$F$2:$F$181,"<="&2023) -> 8.4 | S5: =SUMIFS('Train detail'!$G$2:$G$181,'Train detail'!$B$2:$B$181,$A5,'Train detail'!$C$2:$C$181,$B5,'Train detail'!$F$2:$F$181,"<="&2024) -> 8.4 | T5: =SUMIFS('Train detail'!$G$2:$G$181,'Train detail'!$B$2:$B$181,$A5,'Train detail'!$C$2:$C$181,$B5,'Train detail'!$F$2:$F$181,"<="&2025) -> 8.4
A6: Malaysia | B6: MLNG | C6: 1982 | D6: =SUMIFS('Train detail'!$G$2:$G$181,'Train detail'!$B$2:$B$181,$A6,'Train detail'!$C$2:$C$181,$B6) -> 29.3 | E6: =SUMIFS('Train detail'!$G$2:$G$181,'Train detail'!$B$2:$B$181,$A6,'Train detail'!$C$2:$C$181,$B6,'Train detail'!$F$2:$F$181,"<="&2010) -> 25.7 | F6: =SUMIFS('Train detail'!$G$2:$G$181,'Train detail'!$B$2:$B$181,$A6,'Train detail'!$C$2:$C$181,$B6,'Train detail'!$F$2:$F$181,"<="&2011) -> 25.7 | G6: =SUMIFS('Train detail'!$G$2:$G$181,'Train detail'!$B$2:$B$181,$A6,'Train detail'!$C$2:$C$181,$B6,'Train detail'!$F$2:$F$181,"<="&2012) -> 25.7 | H6: =SUMIFS('Train detail'!$G$2:$G$181,'Train detail'!$B$2:$B$181,$A6,'Train detail'!$C$2:$C$181,$B6,'Train detail'!$F$2:$F$181,"<="&2013) -> 25.7 | I6: =SUMIFS('Train detail'!$G$2:$G$181,'Train detail'!$B$2:$B$181,$A6,'Train detail'!$C$2:$C$181,$B6,'Train detail'!$F$2:$F$181,"<="&2014) -> 25.7 | J6: =SUMIFS('Train detail'!$G$2:$G$181,'Train detail'!$B$2:$B$181,$A6,'Train detail'!$C$2:$C$181,$B6,'Train detail'!$F$2:$F$181,"<="&2015) -> 25.7 | K6: =SUMIFS('Train detail'!$G$2:$G$181,'Train detail'!$B$2:$B$181,$A6,'Train detail'!$C$2:$C$181,$B6,'Train detail'!$F$2:$F$181,"<="&2016) -> 25.7 | L6: =SUMIFS('Train detail'!$G$2:$G$181,'Train detail'!$B$2:$B$181,$A6,'Train detail'!$C$2:$C$181,$B6,'Train detail'!$F$2:$F$181,"<="&2017) -> 29.3 | M6: =SUMIFS('Train detail'!$G$2:$G$181,'Train detail'!$B$2:$B$181,$A6,'Train detail'!$C$2:$C$181,$B6,'Train detail'!$F$2:$F$181,"<="&2018) -> 29.3 | N6: =SUMIFS('Train detail'!$G$2:$G$181,'Train detail'!$B$2:$B$181,$A6,'Train detail'!$C$2:$C$181,$B6,'Train detail'!$F$2:$F$181,"<="&2019) -> 29.3 | O6: =SUMIFS('Train detail'!$G$2:$G$181,'Train detail'!$B$2:$B$181,$A6,'Train detail'!$C$2:$C$181,$B6,'Train detail'!$F$2:$F$181,"<="&2020) -> 29.3 | P6: =SUMIFS('Train detail'!$G$2:$G$181,'Train detail'!$B$2:$B$181,$A6,'Train detail'!$C$2:$C$181,$B6,'Train detail'!$F$2:$F$181,"<="&2021) -> 29.3 | Q6: =SUMIFS('Train detail'!$G$2:$G$181,'Train detail'!$B$2:$B$181,$A6,'Train detail'!$C$2:$C$181,$B6,'Train detail'!$F$2:$F$181,"<="&2022) -> 29.3 | R6: =SUMIFS('Train detail'!$G$2:$G$181,'Train detail'!$B$2:$B$181,$A6,'Train detail'!$C$2:$C$181,$B6,'Train detail'!$F$2:$F$181,"<="&2023) -> 29.3 | S6: =SUMIFS('Train detail'!$G$2:$G$181,'Train detail'!$B$2:$B$181,$A6,'Train detail'!$C$2:$C$181,$B6,'Train detail'!$F$2:$F$181,"<="&2024) -> 29.3 | T6: =SUMIFS('Train detail'!$G$2:$G$181,'Train detail'!$B$2:$B$181,$A6,'Train detail'!$C$2:$C$181,$B6,'Train detail'!$F$2:$F$181,"<="&2025) -> 29.3
A7: Indonesia | B7: Bontang LNG | C7: 1983 | D7: =SUMIFS('Train detail'!$G$2:$G$181,'Train detail'!$B$2:$B$181,$A7,'Train detail'!$C$2:$C$181,$B7) -> 16.95 | E7: =SUMIFS('Train detail'!$G$2:$G$181,'Train detail'!$B$2:$B$181,$A7,'Train detail'!$C$2:$C$181,$B7,'Train detail'!$F$2:$F$181,"<="&2010) -> 16.95 | F7: =SUMIFS('Train detail'!$G$2:$G$181,'Train detail'!$B$2:$B$181,$A7,'Train detail'!$C$2:$C$181,$B7,'Train detail'!$F$2:$F$181,"<="&2011) -> 16.95 | G7: =SUMIFS('Train detail'!$G$2:$G$181,'Train detail'!$B$2:$B$181,$A7,'Train detail'!$C$2:$C$181,$B7,'Train detail'!$F$2:$F$181,"<="&2012) -> 16.95 | H7: =SUMIFS('Train detail'!$G$2:$G$181,'Train detail'!$B$2:$B$181,$A7,'Train detail'!$C$2:$C$181,$B7,'Train detail'!$F$2:$F$181,"<="&2013) -> 16.95 | I7: =SUMIFS('Train detail'!$G$2:$G$181,'Train detail'!$B$2:$B$181,$A7,'Train detail'!$C$2:$C$181,$B7,'Train detail'!$F$2:$F$181,"<="&2014) -> 16.95 | J7: =SUMIFS('Train detail'!$G$2:$G$181,'Train detail'!$B$2:$B$181,$A7,'Train detail'!$C$2:$C$181,$B7,'Train detail'!$F$2:$F$181,"<="&2015) -> 16.95 | K7: =SUMIFS('Train detail'!$G$2:$G$181,'Train detail'!$B$2:$B$181,$A7,'Train detail'!$C$2:$C$181,$B7,'Train detail'!$F$2:$F$181,"<="&2016) -> 16.95 | L7: =SUMIFS('Train detail'!$G$2:$G$181,'Train detail'!$B$2:$B$181,$A7,'Train detail'!$C$2:$C$181,$B7,'Train detail'!$F$2:$F$181,"<="&2017) -> 16.95 | M7: =SUMIFS('Train detail'!$G$2:$G$181,'Train detail'!$B$2:$B$181,$A7,'Train detail'!$C$2:$C$181,$B7,'Train detail'!$F$2:$F$181,"<="&2018) -> 16.95 | N7: =SUMIFS('Train detail'!$G$2:$G$181,'Train detail'!$B$2:$B$181,$A7,'Train detail'!$C$2:$C$181,$B7,'Train detail'!$F$2:$F$181,"<="&2019) -> 16.95 | O7: =SUMIFS('Train detail'!$G$2:$G$181,'Train detail'!$B$2:$B$181,$A7,'Train detail'!$C$2:$C$181,$B7,'Train detail'!$F$2:$F$181,"<="&2020) -> 16.95 | P7: =SUMIFS('Train detail'!$G$2:$G$181,'Train detail'!$B$2:$B$181,$A7,'Train detail'!$C$2:$C$181,$B7,'Train detail'!$F$2:$F$181,"<="&2021) -> 16.95 | Q7: =SUMIFS('Train detail'!$G$2:$G$181,'Train detail'!$B$2:$B$181,$A7,'Train detail'!$C$2:$C$181,$B7,'Train detail'!$F$2:$F$181,"<="&2022) -> 16.95 | R7: =SUMIFS('Train detail'!$G$2:$G$181,'Train detail'!$B$2:$B$181,$A7,'Train detail'!$C$2:$C$181,$B7,'Train detail'!$F$2:$F$181,"<="&2023) -> 16.95 | S7: =SUMIFS('Train detail'!$G$2:$G$181,'Train detail'!$B$2:$B$181,$A7,'Train detail'!$C$2:$C$181,$B7,'Train detail'!$F$2:$F$181,"<="&2024) -> 16.95 | T7: =SUMIFS('Train detail'!$G$2:$G$181,'Train detail'!$B$2:$B$181,$A7,'Train detail'!$C$2:$C$181,$B7,'Train detail'!$F$2:$F$181,"<="&2025) -> 16.95
A8: Australia | B8: North West Shelf LNG | C8: 1989 | D8: =SUMIFS('Train detail'!$G$2:$G$181,'Train detail'!$B$2:$B$181,$A8,'Train detail'!$C$2:$C$181,$B8) -> 14.2 | E8: =SUMIFS('Train detail'!$G$2:$G$181,'Train detail'!$B$2:$B$181,$A8,'Train detail'!$C$2:$C$181,$B8,'Train detail'!$F$2:$F$181,"<="&2010) -> 14.2 | F8: =SUMIFS('Train detail'!$G$2:$G$181,'Train detail'!$B$2:$B$181,$A8,'Train detail'!$C$2:$C$181,$B8,'Train detail'!$F$2:$F$181,"<="&2011) -> 14.2 | G8: =SUMIFS('Train detail'!$G$2:$G$181,'Train detail'!$B$2:$B$181,$A8,'Train detail'!$C$2:$C$181,$B8,'Train detail'!$F$2:$F$181,"<="&2012) -> 14.2 | H8: =SUMIFS('Train detail'!$G$2:$G$181,'Train detail'!$B$2:$B$181,$A8,'Train detail'!$C$2:$C$181,$B8,'Train detail'!$F$2:$F$181,"<="&2013) -> 14.2 | I8: =SUMIFS('Train detail'!$G$2:$G$181,'Train detail'!$B$2:$B$181,$A8,'Train detail'!$C$2:$C$181,$B8,'Train detail'!$F$2:$F$181,"<="&2014) -> 14.2 | J8: =SUMIFS('Train detail'!$G$2:$G$181,'Train detail'!$B$2:$B$181,$A8,'Train detail'!$C$2:$C$181,$B8,'Train detail'!$F$2:$F$181,"<="&2015) -> 14.2 | K8: =SUMIFS('Train detail'!$G$2:$G$181,'Train detail'!$B$2:$B$181,$A8,'Train detail'!$C$2:$C$181,$B8,'Train detail'!$F$2:$F$181,"<="&2016) -> 14.2 | L8: =SUMIFS('Train detail'!$G$2:$G$181,'Train detail'!$B$2:$B$181,$A8,'Train detail'!$C$2:$C$181,$B8,'Train detail'!$F$2:$F$181,"<="&2017) -> 14.2 | M8: =SUMIFS('Train detail'!$G$2:$G$181,'Train detail'!$B$2:$B$181,$A8,'Train detail'!$C$2:$C$181,$B8,'Train detail'!$F$2:$F$181,"<="&2018) -> 14.2 | N8: =SUMIFS('Train detail'!$G$2:$G$181,'Train detail'!$B$2:$B$181,$A8,'Train detail'!$C$2:$C$181,$B8,'Train detail'!$F$2:$F$181,"<="&2019) -> 14.2 | O8: =SUMIFS('Train detail'!$G$2:$G$181,'Train detail'!$B$2:$B$181,$A8,'Train detail'!$C$2:$C$181,$B8,'Train detail'!$F$2:$F$181,"<="&2020) -> 14.2 | P8: =SUMIFS('Train detail'!$G$2:$G$181,'Train detail'!$B$2:$B$181,$A8,'Train detail'!$C$2:$C$181,$B8,'Train detail'!$F$2:$F$181,"<="&2021) -> 14.2 | Q8: =SUMIFS('Train detail'!$G$2:$G$181,'Train detail'!$B$2:$B$181,$A8,'Train detail'!$C$2:$C$181,$B8,'Train detail'!$F$2:$F$181,"<="&2022) -> 14.2 | R8: =SUMIFS('Train detail'!$G$2:$G$181,'Train detail'!$B$2:$B$181,$A8,'Train detail'!$C$2:$C$181,$B8,'Train detail'!$F$2:$F$181,"<="&2023) -> 14.2 | S8: =SUMIFS('Train detail'!$G$2:$G$181,'Train detail'!$B$2:$B$181,$A8,'Train detail'!$C$2:$C$181,$B8,'Train detail'!$F$2:$F$181,"<="&2024) -> 14.2 | T8: =SUMIFS('Train detail'!$G$2:$G$181,'Train detail'!$B$2:$B$181,$A8,'Train detail'!$C$2:$C$181,$B8,'Train detail'!$F$2:$F$181,"<="&2025) -> 14.2
A9: Qatar | B9: QatarGas LNG | C9: 1996 | D9: =SUMIFS('Train detail'!$G$2:$G$181,'Train detail'!$B$2:$B$181,$A9,'Train detail'!$C$2:$C$181,$B9) -> 77.1 | E9: =SUMIFS('Train detail'!$G$2:$G$181,'Train detail'!$B$2:$B$181,$A9,'Train detail'!$C$2:$C$181,$B9,'Train detail'!$F$2:$F$181,"<="&2010) -> 69.3 | F9: =SUMIFS('Train detail'!$G$2:$G$181,'Train detail'!$B$2:$B$181,$A9,'Train detail'!$C$2:$C$181,$B9,'Train detail'!$F$2:$F$181,"<="&2011) -> 77.1 | G9: =SUMIFS('Train detail'!$G$2:$G$181,'Train detail'!$B$2:$B$181,$A9,'Train detail'!$C$2:$C$181,$B9,'Train detail'!$F$2:$F$181,"<="&2012) -> 77.1 | H9: =SUMIFS('Train detail'!$G$2:$G$181,'Train detail'!$B$2:$B$181,$A9,'Train detail'!$C$2:$C$181,$B9,'Train detail'!$F$2:$F$181,"<="&2013) -> 77.1 | I9: =SUMIFS('Train detail'!$G$2:$G$181,'Train detail'!$B$2:$B$181,$A9,'Train detail'!$C$2:$C$181,$B9,'Train detail'!$F$2:$F$181,"<="&2014) -> 77.1 | J9: =SUMIFS('Train detail'!$G$2:$G$181,'Train detail'!$B$2:$B$181,$A9,'Train detail'!$C$2:$C$181,$B9,'Train detail'!$F$2:$F$181,"<="&2015) -> 77.1 | K9: =SUMIFS('Train detail'!$G$2:$G$181,'Train detail'!$B$2:$B$181,$A9,'Train detail'!$C$2:$C$181,$B9,'Train detail'!$F$2:$F$181,"<="&2016) -> 77.1 | L9: =SUMIFS('Train detail'!$G$2:$G$181,'Train detail'!$B$2:$B$181,$A9,'Train detail'!$C$2:$C$181,$B9,'Train detail'!$F$2:$F$181,"<="&2017) -> 77.1 | M9: =SUMIFS('Train detail'!$G$2:$G$181,'Train detail'!$B$2:$B$181,$A9,'Train detail'!$C$2:$C$181,$B9,'Train detail'!$F$2:$F$181,"<="&2018) -> 77.1 | N9: =SUMIFS('Train detail'!$G$2:$G$181,'Train detail'!$B$2:$B$181,$A9,'Train detail'!$C$2:$C$181,$B9,'Train detail'!$F$2:$F$181,"<="&2019) -> 77.1 | O9: =SUMIFS('Train detail'!$G$2:$G$181,'Train detail'!$B$2:$B$181,$A9,'Train detail'!$C$2:$C$181,$B9,'Train detail'!$F$2:$F$181,"<="&2020) -> 77.1 | P9: =SUMIFS('Train detail'!$G$2:$G$181,'Train detail'!$B$2:$B$181,$A9,'Train detail'!$C$2:$C$181,$B9,'Train detail'!$F$2:$F$181,"<="&2021) -> 77.1 | Q9: =SUMIFS('Train detail'!$G$2:$G$181,'Train detail'!$B$2:$B$181,$A9,'Train detail'!$C$2:$C$181,$B9,'Train detail'!$F$2:$F$181,"<="&2022) -> 77.1 | R9: =SUMIFS('Train detail'!$G$2:$G$181,'Train detail'!$B$2:$B$181,$A9,'Train detail'!$C$2:$C$181,$B9,'Train detail'!$F$2:$F$181,"<="&2023) -> 77.1 | S9: =SUMIFS('Train detail'!$G$2:$G$181,'Train detail'!$B$2:$B$181,$A9,'Train detail'!$C$2:$C$181,$B9,'Train detail'!$F$2:$F$181,"<="&2024) -> 77.1 | T9: =SUMIFS('Train detail'!$G$2:$G$181,'Train detail'!$B$2:$B$181,$A9,'Train detail'!$C$2:$C$181,$B9,'Train detail'!$F$2:$F$181,"<="&2025) -> 77.1
A10: Nigeria | B10: NLNG | C10: 1999 | D10: =SUMIFS('Train detail'!$G$2:$G$181,'Train detail'!$B$2:$B$181,$A10,'Train detail'!$C$2:$C$181,$B10) -> 22.2 | E10: =SUMIFS('Train detail'!$G$2:$G$181,'Train detail'!$B$2:$B$181,$A10,'Train detail'!$C$2:$C$181,$B10,'Train detail'!$F$2:$F$181,"<="&2010) -> 22.2 | F10: =SUMIFS('Train detail'!$G$2:$G$181,'Train detail'!$B$2:$B$181,$A10,'Train detail'!$C$2:$C$181,$B10,'Train detail'!$F$2:$F$181,"<="&2011) -> 22.2 | G10: =SUMIFS('Train detail'!$G$2:$G$181,'Train detail'!$B$2:$B$181,$A10,'Train detail'!$C$2:$C$181,$B10,'Train detail'!$F$2:$F$181,"<="&2012) -> 22.2 | H10: =SUMIFS('Train detail'!$G$2:$G$181,'Train detail'!$B$2:$B$181,$A10,'Train detail'!$C$2:$C$181,$B10,'Train detail'!$F$2:$F$181,"<="&2013) -> 22.2 | I10: =SUMIFS('Train detail'!$G$2:$G$181,'Train detail'!$B$2:$B$181,$A10,'Train detail'!$C$2:$C$181,$B10,'Train detail'!$F$2:$F$181,"<="&2014) -> 22.2 | J10: =SUMIFS('Train detail'!$G$2:$G$181,'Train detail'!$B$2:$B$181,$A10,'Train detail'!$C$2:$C$181,$B10,'Train detail'!$F$2:$F$181,"<="&2015) -> 22.2 | K10: =SUMIFS('Train detail'!$G$2:$G$181,'Train detail'!$B$2:$B$181,$A10,'Train detail'!$C$2:$C$181,$B10,'Train detail'!$F$2:$F$181,"<="&2016) -> 22.2 | L10: =SUMIFS('Train detail'!$G$2:$G$181,'Train detail'!$B$2:$B$181,$A10,'Train detail'!$C$2:$C$181,$B10,'Train detail'!$F$2:$F$181,"<="&2017) -> 22.2 | M10: =SUMIFS('Train detail'!$G$2:$G$181,'Train detail'!$B$2:$B$181,$A10,'Train detail'!$C$2:$C$181,$B10,'Train detail'!$F$2:$F$181,"<="&2018) -> 22.2 | N10: =SUMIFS('Train detail'!$G$2:$G$181,'Train detail'!$B$2:$B$181,$A10,'Train detail'!$C$2:$C$181,$B10,'Train detail'!$F$2:$F$181,"<="&2019) -> 22.2 | O10: =SUMIFS('Train detail'!$G$2:$G$181,'Train detail'!$B$2:$B$181,$A10,'Train detail'!$C$2:$C$181,$B10,'Train detail'!$F$2:$F$181,"<="&2020) -> 22.2 | P10: =SUMIFS('Train detail'!$G$2:$G$181,'Train detail'!$B$2:$B$181,$A10,'Train detail'!$C$2:$C$181,$B10,'Train detail'!$F$2:$F$181,"<="&2021) -> 22.2 | Q10: =SUMIFS('Train detail'!$G$2:$G$181,'Train detail'!$B$2:$B$181,$A10,'Train detail'!$C$2:$C$181,$B10,'Train detail'!$F$2:$F$181,"<="&2022) -> 22.2 | R10: =SUMIFS('Train detail'!$G$2:$G$181,'Train detail'!$B$2:$B$181,$A10,'Train detail'!$C$2:$C$181,$B10,'Train detail'!$F$2:$F$181,"<="&2023) -> 22.2 | S10: =SUMIFS('Train detail'!$G$2:$G$181,'Train detail'!$B$2:$B$181,$A10,'Train detail'!$C$2:$C$181,$B10,'Train detail'!$F$2:$F$181,"<="&2024) -> 22.2 | T10: =SUMIFS('Train detail'!$G$2:$G$181,'Train detail'!$B$2:$B$181,$A10,'Train detail'!$C$2:$C$181,$B10,'Train detail'!$F$2:$F$181,"<="&2025) -> 22.2
A11: Oman | B11: Oman LNG | C11: 2000 | D11: =SUMIFS('Train detail'!$G$2:$G$181,'Train detail'!$B$2:$B$181,$A11,'Train detail'!$C$2:$C$181,$B11) -> 10.4 | E11: =SUMIFS('Train detail'!$G$2:$G$181,'Train detail'!$B$2:$B$181,$A11,'Train detail'!$C$2:$C$181,$B11,'Train detail'!$F$2:$F$181,"<="&2010) -> 10.4 | F11: =SUMIFS('Train detail'!$G$2:$G$181,'Train detail'!$B$2:$B$181,$A11,'Train detail'!$C$2:$C$181,$B11,'Train detail'!$F$2:$F$181,"<="&2011) -> 10.4 | G11: =SUMIFS('Train detail'!$G$2:$G$181,'Train detail'!$B$2:$B$181,$A11,'Train detail'!$C$2:$C$181,$B11,'Train detail'!$F$2:$F$181,"<="&2012) -> 10.4 | H11: =SUMIFS('Train detail'!$G$2:$G$181,'Train detail'!$B$2:$B$181,$A11,'Train detail'!$C$2:$C$181,$B11,'Train detail'!$F$2:$F$181,"<="&2013) -> 10.4 | I11: =SUMIFS('Train detail'!$G$2:$G$181,'Train detail'!$B$2:$B$181,$A11,'Train detail'!$C$2:$C$181,$B11,'Train detail'!$F$2:$F$181,"<="&2014) -> 10.4 | J11: =SUMIFS('Train detail'!$G$2:$G$181,'Train detail'!$B$2:$B$181,$A11,'Train detail'!$C$2:$C$181,$B11,'Train detail'!$F$2:$F$181,"<="&2015) -> 10.4 | K11: =SUMIFS('Train detail'!$G$2:$G$181,'Train detail'!$B$2:$B$181,$A11,'Train detail'!$C$2:$C$181,$B11,'Train detail'!$F$2:$F$181,"<="&2016) -> 10.4 | L11: =SUMIFS('Train detail'!$G$2:$G$181,'Train detail'!$B$2:$B$181,$A11,'Train detail'!$C$2:$C$181,$B11,'Train detail'!$F$2:$F$181,"<="&2017) -> 10.4 | M11: =SUMIFS('Train detail'!$G$2:$G$181,'Train detail'!$B$2:$B$181,$A11,'Train detail'!$C$2:$C$181,$B11,'Train detail'!$F$2:$F$181,"<="&2018) -> 10.4 | N11: =SUMIFS('Train detail'!$G$2:$G$181,'Train detail'!$B$2:$B$181,$A11,'Train detail'!$C$2:$C$181,$B11,'Train detail'!$F$2:$F$181,"<="&2019) -> 10.4 | O11: =SUMIFS('Train detail'!$G$2:$G$181,'Train detail'!$B$2:$B$181,$A11,'Train detail'!$C$2:$C$181,$B11,'Train detail'!$F$2:$F$181,"<="&2020) -> 10.4 | P11: =SUMIFS('Train detail'!$G$2:$G$181,'Train detail'!$B$2:$B$181,$A11,'Train detail'!$C$2:$C$181,$B11,'Train detail'!$F$2:$F$181,"<="&2021) -> 10.4 | Q11: =SUMIFS('Train detail'!$G$2:$G$181,'Train detail'!$B$2:$B$181,$A11,'Train detail'!$C$2:$C$181,$B11,'Train detail'!$F$2:$F$181,"<="&2022) -> 10.4 | R11: =SUMIFS('Train detail'!$G$2:$G$181,'Train detail'!$B$2:$B$181,$A11,'Train detail'!$C$2:$C$181,$B11,'Train detail'!$F$2:$F$181,"<="&2023) -> 10.4 | S11: =SUMIFS('Train detail'!$G$2:$G$181,'Train detail'!$B$2:$B$181,$A11,'Train detail'!$C$2:$C$181,$B11,'Train detail'!$F$2:$F$181,"<="&2024) -> 10.4 | T11: =SUMIFS('Train detail'!$G$2:$G$181,'Train detail'!$B$2:$B$181,$A11,'Train detail'!$C$2:$C$181,$B11,'Train detail'!$F$2:$F$181,"<="&2025) -> 10.4
A12: Trinidad and Tobago | B12: Atlantic LNG | C12: 2002 | D12: =SUMIFS('Train detail'!$G$2:$G$181,'Train detail'!$B$2:$B$181,$A12,'Train detail'!$C$2:$C$181,$B12) -> 11.8 | E12: =SUMIFS('Train detail'!$G$2:$G$181,'Train detail'!$B$2:$B$181,$A12,'Train detail'!$C$2:$C$181,$B12,'Train detail'!$F$2:$F$181,"<="&2010) -> 11.8 | F12: =SUMIFS('Train detail'!$G$2:$G$181,'Train detail'!$B$2:$B$181,$A12,'Train detail'!$C$2:$C$181,$B12,'Train detail'!$F$2:$F$181,"<="&2011) -> 11.8 | G12: =SUMIFS('Train detail'!$G$2:$G$181,'Train detail'!$B$2:$B$181,$A12,'Train detail'!$C$2:$C$181,$B12,'Train detail'!$F$2:$F$181,"<="&2012) -> 11.8 | H12: =SUMIFS('Train detail'!$G$2:$G$181,'Train detail'!$B$2:$B$181,$A12,'Train detail'!$C$2:$C$181,$B12,'Train detail'!$F$2:$F$181,"<="&2013) -> 11.8 | I12: =SUMIFS('Train detail'!$G$2:$G$181,'Train detail'!$B$2:$B$181,$A12,'Train detail'!$C$2:$C$181,$B12,'Train detail'!$F$2:$F$181,"<="&2014) -> 11.8 | J12: =SUMIFS('Train detail'!$G$2:$G$181,'Train detail'!$B$2:$B$181,$A12,'Train detail'!$C$2:$C$181,$B12,'Train detail'!$F$2:$F$181,"<="&2015) -> 11.8 | K12: =SUMIFS('Train detail'!$G$2:$G$181,'Train detail'!$B$2:$B$181,$A12,'Train detail'!$C$2:$C$181,$B12,'Train detail'!$F$2:$F$181,"<="&2016) -> 11.8 | L12: =SUMIFS('Train detail'!$G$2:$G$181,'Train detail'!$B$2:$B$181,$A12,'Train detail'!$C$2:$C$181,$B12,'Train detail'!$F$2:$F$181,"<="&2017) -> 11.8 | M12: =SUMIFS('Train detail'!$G$2:$G$181,'Train detail'!$B$2:$B$181,$A12,'Train detail'!$C$2:$C$181,$B12,'Train detail'!$F$2:$F$181,"<="&2018) -> 11.8 | N12: =SUMIFS('Train detail'!$G$2:$G$181,'Train detail'!$B$2:$B$181,$A12,'Train detail'!$C$2:$C$181,$B12,'Train detail'!$F$2:$F$181,"<="&2019) -> 11.8 | O12: =SUMIFS('Train detail'!$G$2:$G$181,'Train detail'!$B$2:$B$181,$A12,'Train detail'!$C$2:$C$181,$B12,'Train detail'!$F$2:$F$181,"<="&2020) -> 11.8 | P12: =SUMIFS('Train detail'!$G$2:$G$181,'Train detail'!$B$2:$B$181,$A12,'Train detail'!$C$2:$C$181,$B12,'Train detail'!$F$2:$F$181,"<="&2021) -> 11.8 | Q12: =SUMIFS('Train detail'!$G$2:$G$181,'Train detail'!$B$2:$B$181,$A12,'Train detail'!$C$2:$C$181,$B12,'Train detail'!$F$2:$F$181,"<="&2022) -> 11.8 | R12: =SUMIFS('Train detail'!$G$2:$G$181,'Train detail'!$B$2:$B$181,$A12,'Train detail'!$C$2:$C$181,$B12,'Train detail'!$F$2:$F$181,"<="&2023) -> 11.8 | S12: =SUMIFS('Train detail'!$G$2:$G$181,'Train detail'!$B$2:$B$181,$A12,'Train detail'!$C$2:$C$181,$B12,'Train detail'!$F$2:$F$181,"<="&2024) -> 11.8 | T12: =SUMIFS('Train detail'!$G$2:$G$181,'Train detail'!$B$2:$B$181,$A12,'Train detail'!$C$2:$C$181,$B12,'Train detail'!$F$2:$F$181,"<="&2025) -> 11.8
A13: Egypt | B13: Damietta LNG | C13: 2005 | D13: =SUMIFS('Train detail'!$G$2:$G$181,'Train detail'!$B$2:$B$181,$A13,'Train detail'!$C$2:$C$181,$B13) -> 5 | E13: =SUMIFS('Train detail'!$G$2:$G$181,'Train detail'!$B$2:$B$181,$A13,'Train detail'!$C$2:$C$181,$B13,'Train detail'!$F$2:$F$181,"<="&2010) -> 5 | F13: =SUMIFS('Train detail'!$G$2:$G$181,'Train detail'!$B$2:$B$181,$A13,'Train detail'!$C$2:$C$181,$B13,'Train detail'!$F$2:$F$181,"<="&2011) -> 5 | G13: =SUMIFS('Train detail'!$G$2:$G$181,'Train detail'!$B$2:$B$181,$A13,'Train detail'!$C$2:$C$181,$B13,'Train detail'!$F$2:$F$181,"<="&2012) -> 5 | H13: =SUMIFS('Train detail'!$G$2:$G$181,'Train detail'!$B$2:$B$181,$A13,'Train detail'!$C$2:$C$181,$B13,'Train detail'!$F$2:$F$181,"<="&2013) -> 5 | I13: =SUMIFS('Train detail'!$G$2:$G$181,'Train detail'!$B$2:$B$181,$A13,'Train detail'!$C$2:$C$181,$B13,'Train detail'!$F$2:$F$181,"<="&2014) -> 5 | J13: =SUMIFS('Train detail'!$G$2:$G$181,'Train detail'!$B$2:$B$181,$A13,'Train detail'!$C$2:$C$181,$B13,'Train detail'!$F$2:$F$181,"<="&2015) -> 5 | K13: =SUMIFS('Train detail'!$G$2:$G$181,'Train detail'!$B$2:$B$181,$A13,'Train detail'!$C$2:$C$181,$B13,'Train detail'!$F$2:$F$181,"<="&2016) -> 5 | L13: =SUMIFS('Train detail'!$G$2:$G$181,'Train detail'!$B$2:$B$181,$A13,'Train detail'!$C$2:$C$181,$B13,'Train detail'!$F$2:$F$181,"<="&2017) -> 5 | M13: =SUMIFS('Train detail'!$G$2:$G$181,'Train detail'!$B$2:$B$181,$A13,'Train detail'!$C$2:$C$181,$B13,'Train detail'!$F$2:$F$181,"<="&2018) -> 5 | N13: =SUMIFS('Train detail'!$G$2:$G$181,'Train detail'!$B$2:$B$181,$A13,'Train detail'!$C$2:$C$181,$B13,'Train detail'!$F$2:$F$181,"<="&2019) -> 5 | O13: =SUMIFS('Train detail'!$G$2:$G$181,'Train detail'!$B$2:$B$181,$A13,'Train detail'!$C$2:$C$181,$B13,'Train detail'!$F$2:$F$181,"<="&2020) -> 5 | P13: =SUMIFS('Train detail'!$G$2:$G$181,'Train detail'!$B$2:$B$181,$A13,'Train detail'!$C$2:$C$181,$B13,'Train detail'!$F$2:$F$181,"<="&2021) -> 5 | Q13: =SUMIFS('Train detail'!$G$2:$G$181,'Train detail'!$B$2:$B$181,$A13,'Train detail'!$C$2:$C$181,$B13,'Train detail'!$F$2:$F$181,"<="&2022) -> 5 | R13: =SUMIFS('Train detail'!$G$2:$G$181,'Train detail'!$B$2:$B$181,$A13,'Train detail'!$C$2:$C$181,$B13,'Train detail'!$F$2:$F$181,"<="&2023) -> 5 | S13: =SUMIFS('Train detail'!$G$2:$G$181,'Train detail'!$B$2:$B$181,$A13,'Train detail'!$C$2:$C$181,$B13,'Train detail'!$F$2:$F$181,"<="&2024) -> 5 | T13: =SUMIFS('Train detail'!$G$2:$G$181,'Train detail'!$B$2:$B$181,$A13,'Train detail'!$C$2:$C$181,$B13,'Train detail'!$F$2:$F$181,"<="&2025) -> 5
... A56: Russia | B56: Arctic LNG 2 | C56: 2025 | D56: =SUMIFS('Train detail'!$G$2:$G$181,'Train detail'!$B$2:$B$181,$A56,'Train detail'!$C$2:$C$181,$B56) -> 6.6 | E56: =SUMIFS('Train detail'!$G$2:$G$181,'Train detail'!$B$2:$B$181,$A56,'Train detail'!$C$2:$C$181,$B56,'Train detail'!$F$2:$F$181,"<="&2010) -> 0 | F56: =SUMIFS('Train detail'!$G$2:$G$181,'Train detail'!$B$2:$B$181,$A56,'Train detail'!$C$2:$C$181,$B56,'Train detail'!$F$2:$F$181,"<="&2011) -> 0 | G56: =SUMIFS('Train detail'!$G$2:$G$181,'Train detail'!$B$2:$B$181,$A56,'Train detail'!$C$2:$C$181,$B56,'Train detail'!$F$2:$F$181,"<="&2012) -> 0 | H56: =SUMIFS('Train detail'!$G$2:$G$181,'Train detail'!$B$2:$B$181,$A56,'Train detail'!$C$2:$C$181,$B56,'Train detail'!$F$2:$F$181,"<="&2013) -> 0 | I56: =SUMIFS('Train detail'!$G$2:$G$181,'Train detail'!$B$2:$B$181,$A56,'Train detail'!$C$2:$C$181,$B56,'Train detail'!$F$2:$F$181,"<="&2014) -> 0 | J56: =SUMIFS('Train detail'!$G$2:$G$181,'Train detail'!$B$2:$B$181,$A56,'Train detail'!$C$2:$C$181,$B56,'Train detail'!$F$2:$F$181,"<="&2015) -> 0 | K56: =SUMIFS('Train detail'!$G$2:$G$181,'Train detail'!$B$2:$B$181,$A56,'Train detail'!$C$2:$C$181,$B56,'Train detail'!$F$2:$F$181,"<="&2016) -> 0 | L56: =SUMIFS('Train detail'!$G$2:$G$181,'Train detail'!$B$2:$B$181,$A56,'Train detail'!$C$2:$C$181,$B56,'Train detail'!$F$2:$F$181,"<="&2017) -> 0 | M56: =SUMIFS('Train detail'!$G$2:$G$181,'Train detail'!$B$2:$B$181,$A56,'Train detail'!$C$2:$C$181,$B56,'Train detail'!$F$2:$F$181,"<="&2018) -> 0 | N56: =SUMIFS('Train detail'!$G$2:$G$181,'Train detail'!$B$2:$B$181,$A56,'Train detail'!$C$2:$C$181,$B56,'Train detail'!$F$2:$F$181,"<="&2019) -> 0 | O56: =SUMIFS('Train detail'!$G$2:$G$181,'Train detail'!$B$2:$B$181,$A56,'Train detail'!$C$2:$C$181,$B56,'Train detail'!$F$2:$F$181,"<="&2020) -> 0 | P56: =SUMIFS('Train detail'!$G$2:$G$181,'Train detail'!$B$2:$B$181,$A56,'Train detail'!$C$2:$C$181,$B56,'Train detail'!$F$2:$F$181,"<="&2021) -> 0 | Q56: =SUMIFS('Train detail'!$G$2:$G$181,'Train detail'!$B$2:$B$181,$A56,'Train detail'!$C$2:$C$181,$B56,'Train detail'!$F$2:$F$181,"<="&2022) -> 0 | R56: =SUMIFS('Train detail'!$G$2:$G$181,'Train detail'!$B$2:$B$181,$A56,'Train detail'!$C$2:$C$181,$B56,'Train detail'!$F$2:$F$181,"<="&2023) -> 0 | S56: =SUMIFS('Train detail'!$G$2:$G$181,'Train detail'!$B$2:$B$181,$A56,'Train detail'!$C$2:$C$181,$B56,'Train detail'!$F$2:$F$181,"<="&2024) -> 0 | T56: =SUMIFS('Train detail'!$G$2:$G$181,'Train detail'!$B$2:$B$181,$A56,'Train detail'!$C$2:$C$181,$B56,'Train detail'!$F$2:$F$181,"<="&2025) -> 6.6
A57: GLOBAL TOTAL | D57: =SUM(D2:D56) -> 524.552 | E57: =SUM(E2:E56) -> 255.77 | F57: =SUM(F2:F56) -> 263.57 | G57: =SUM(G2:G56) -> 268.47 | H57: =SUM(H2:H56) -> 278.17 | I57: =SUM(I2:I56) -> 289.77 | J57: =SUM(J2:J56) -> 304.17 | K57: =SUM(K2:K56) -> 342.67 | ... T57: =SUM(T2:T56) -> 524.552

Sheet Country x Year
A1: Country | B1: First Online | C1: Nameplate end-2025 (Mtpa) | D1: 2010 | E1: 2011 | F1: 2012 | G1: 2013 | H1: 2014 | I1: 2015 | J1: 2016 | K1: 2017 | L1: 2018 | M1: 2019 | N1: 2020 | O1: 2021 | P1: 2022 | Q1: 2023 | R1: 2024 | S1: 2025
A2: Brunei | B2: 1972 | C2: =SUMIFS('Train detail'!$G$2:$G$181,'Train detail'!$B$2:$B$181,$A2) -> 7.2 | D2: =SUMIFS('Train detail'!$G$2:$G$181,'Train detail'!$B$2:$B$181,$A2,'Train detail'!$F$2:$F$181,"<="&2010) -> 7.2 | E2: =SUMIFS('Train detail'!$G$2:$G$181,'Train detail'!$B$2:$B$181,$A2,'Train detail'!$F$2:$F$181,"<="&2011) -> 7.2 | F2: =SUMIFS('Train detail'!$G$2:$G$181,'Train detail'!$B$2:$B$181,$A2,'Train detail'!$F$2:$F$181,"<="&2012) -> 7.2 | G2: =SUMIFS('Train detail'!$G$2:$G$181,'Train detail'!$B$2:$B$181,$A2,'Train detail'!$F$2:$F$181,"<="&2013) -> 7.2 | H2: =SUMIFS('Train detail'!$G$2:$G$181,'Train detail'!$B$2:$B$181,$A2,'Train detail'!$F$2:$F$181,"<="&2014) -> 7.2 | I2: =SUMIFS('Train detail'!$G$2:$G$181,'Train detail'!$B$2:$B$181,$A2,'Train detail'!$F$2:$F$181,"<="&2015) -> 7.2 | J2: =SUMIFS('Train detail'!$G$2:$G$181,'Train detail'!$B$2:$B$181,$A2,'Train detail'!$F$2:$F$181,"<="&2016) -> 7.2 | K2: =SUMIFS('Train detail'!$G$2:$G$181,'Train detail'!$B$2:$B$181,$A2,'Train detail'!$F$2:$F$181,"<="&2017) -> 7.2 | L2: =SUMIFS('Train detail'!$G$2:$G$181,'Train detail'!$B$2:$B$181,$A2,'Train detail'!$F$2:$F$181,"<="&2018) -> 7.2 | M2: =SUMIFS('Train detail'!$G$2:$G$181,'Train detail'!$B$2:$B$181,$A2,'Train detail'!$F$2:$F$181,"<="&2019) -> 7.2 | N2: =SUMIFS('Train detail'!$G$2:$G$181,'Train detail'!$B$2:$B$181,$A2,'Train detail'!$F$2:$F$181,"<="&2020) -> 7.2 | O2: =SUMIFS('Train detail'!$G$2:$G$181,'Train detail'!$B$2:$B$181,$A2,'Train detail'!$F$2:$F$181,"<="&2021) -> 7.2 | P2: =SUMIFS('Train detail'!$G$2:$G$181,'Train detail'!$B$2:$B$181,$A2,'Train detail'!$F$2:$F$181,"<="&2022) -> 7.2 | Q2: =SUMIFS('Train detail'!$G$2:$G$181,'Train detail'!$B$2:$B$181,$A2,'Train detail'!$F$2:$F$181,"<="&2023) -> 7.2 | R2: =SUMIFS('Train detail'!$G$2:$G$181,'Train detail'!$B$2:$B$181,$A2,'Train detail'!$F$2:$F$181,"<="&2024) -> 7.2 | S2: =SUMIFS('Train detail'!$G$2:$G$181,'Train detail'!$B$2:$B$181,$A2,'Train detail'!$F$2:$F$181,"<="&2025) -> 7.2
A3: UAE | B3: 1977 | C3: =SUMIFS('Train detail'!$G$2:$G$181,'Train detail'!$B$2:$B$181,$A3) -> 5.3 | D3: =SUMIFS('Train detail'!$G$2:$G$181,'Train detail'!$B$2:$B$181,$A3,'Train detail'!$F$2:$F$181,"<="&2010) -> 5.3 | E3: =SUMIFS('Train detail'!$G$2:$G$181,'Train detail'!$B$2:$B$181,$A3,'Train detail'!$F$2:$F$181,"<="&2011) -> 5.3 | F3: =SUMIFS('Train detail'!$G$2:$G$181,'Train detail'!$B$2:$B$181,$A3,'Train detail'!$F$2:$F$181,"<="&2012) -> 5.3 | G3: =SUMIFS('Train detail'!$G$2:$G$181,'Train detail'!$B$2:$B$181,$A3,'Train detail'!$F$2:$F$181,"<="&2013) -> 5.3 | H3: =SUMIFS('Train detail'!$G$2:$G$181,'Train detail'!$B$2:$B$181,$A3,'Train detail'!$F$2:$F$181,"<="&2014) -> 5.3 | I3: =SUMIFS('Train detail'!$G$2:$G$181,'Train detail'!$B$2:$B$181,$A3,'Train detail'!$F$2:$F$181,"<="&2015) -> 5.3 | J3: =SUMIFS('Train detail'!$G$2:$G$181,'Train detail'!$B$2:$B$181,$A3,'Train detail'!$F$2:$F$181,"<="&2016) -> 5.3 | K3: =SUMIFS('Train detail'!$G$2:$G$181,'Train detail'!$B$2:$B$181,$A3,'Train detail'!$F$2:$F$181,"<="&2017) -> 5.3 | L3: =SUMIFS('Train detail'!$G$2:$G$181,'Train detail'!$B$2:$B$181,$A3,'Train detail'!$F$2:$F$181,"<="&2018) -> 5.3 | M3: =SUMIFS('Train detail'!$G$2:$G$181,'Train detail'!$B$2:$B$181,$A3,'Train detail'!$F$2:$F$181,"<="&2019) -> 5.3 | N3: =SUMIFS('Train detail'!$G$2:$G$181,'Train detail'!$B$2:$B$181,$A3,'Train detail'!$F$2:$F$181,"<="&2020) -> 5.3 | O3: =SUMIFS('Train detail'!$G$2:$G$181,'Train detail'!$B$2:$B$181,$A3,'Train detail'!$F$2:$F$181,"<="&2021) -> 5.3 | P3: =SUMIFS('Train detail'!$G$2:$G$181,'Train detail'!$B$2:$B$181,$A3,'Train detail'!$F$2:$F$181,"<="&2022) -> 5.3 | Q3: =SUMIFS('Train detail'!$G$2:$G$181,'Train detail'!$B$2:$B$181,$A3,'Train detail'!$F$2:$F$181,"<="&2023) -> 5.3 | R3: =SUMIFS('Train detail'!$G$2:$G$181,'Train detail'!$B$2:$B$181,$A3,'Train detail'!$F$2:$F$181,"<="&2024) -> 5.3 | S3: =SUMIFS('Train detail'!$G$2:$G$181,'Train detail'!$B$2:$B$181,$A3,'Train detail'!$F$2:$F$181,"<="&2025) -> 5.3
A4: Algeria | B4: 1978 | C4: =SUMIFS('Train detail'!$G$2:$G$181,'Train detail'!$B$2:$B$181,$A4) -> 25.5 | D4: =SUMIFS('Train detail'!$G$2:$G$181,'Train detail'!$B$2:$B$181,$A4,'Train detail'!$F$2:$F$181,"<="&2010) -> 16.3 | E4: =SUMIFS('Train detail'!$G$2:$G$181,'Train detail'!$B$2:$B$181,$A4,'Train detail'!$F$2:$F$181,"<="&2011) -> 16.3 | F4: =SUMIFS('Train detail'!$G$2:$G$181,'Train detail'!$B$2:$B$181,$A4,'Train detail'!$F$2:$F$181,"<="&2012) -> 16.3 | G4: =SUMIFS('Train detail'!$G$2:$G$181,'Train detail'!$B$2:$B$181,$A4,'Train detail'!$F$2:$F$181,"<="&2013) -> 20.8 | H4: =SUMIFS('Train detail'!$G$2:$G$181,'Train detail'!$B$2:$B$181,$A4,'Train detail'!$F$2:$F$181,"<="&2014) -> 25.5 | I4: =SUMIFS('Train detail'!$G$2:$G$181,'Train detail'!$B$2:$B$181,$A4,'Train detail'!$F$2:$F$181,"<="&2015) -> 25.5 | J4: =SUMIFS('Train detail'!$G$2:$G$181,'Train detail'!$B$2:$B$181,$A4,'Train detail'!$F$2:$F$181,"<="&2016) -> 25.5 | K4: =SUMIFS('Train detail'!$G$2:$G$181,'Train detail'!$B$2:$B$181,$A4,'Train detail'!$F$2:$F$181,"<="&2017) -> 25.5 | L4: =SUMIFS('Train detail'!$G$2:$G$181,'Train detail'!$B$2:$B$181,$A4,'Train detail'!$F$2:$F$181,"<="&2018) -> 25.5 | M4: =SUMIFS('Train detail'!$G$2:$G$181,'Train detail'!$B$2:$B$181,$A4,'Train detail'!$F$2:$F$181,"<="&2019) -> 25.5 | N4: =SUMIFS('Train detail'!$G$2:$G$181,'Train detail'!$B$2:$B$181,$A4,'Train detail'!$F$2:$F$181,"<="&2020) -> 25.5 | O4: =SUMIFS('Train detail'!$G$2:$G$181,'Train detail'!$B$2:$B$181,$A4,'Train detail'!$F$2:$F$181,"<="&2021) -> 25.5 | P4: =SUMIFS('Train detail'!$G$2:$G$181,'Train detail'!$B$2:$B$181,$A4,'Train detail'!$F$2:$F$181,"<="&2022) -> 25.5 | Q4: =SUMIFS('Train detail'!$G$2:$G$181,'Train detail'!$B$2:$B$181,$A4,'Train detail'!$F$2:$F$181,"<="&2023) -> 25.5 | R4: =SUMIFS('Train detail'!$G$2:$G$181,'Train detail'!$B$2:$B$181,$A4,'Train detail'!$F$2:$F$181,"<="&2024) -> 25.5 | S4: =SUMIFS('Train detail'!$G$2:$G$181,'Train detail'!$B$2:$B$181,$A4,'Train detail'!$F$2:$F$181,"<="&2025) -> 25.5
A5: Malaysia | B5: 1982 | C5: =SUMIFS('Train detail'!$G$2:$G$181,'Train detail'!$B$2:$B$181,$A5) -> 32 | D5: =SUMIFS('Train detail'!$G$2:$G$181,'Train detail'!$B$2:$B$181,$A5,'Train detail'!$F$2:$F$181,"<="&2010) -> 25.7 | E5: =SUMIFS('Train detail'!$G$2:$G$181,'Train detail'!$B$2:$B$181,$A5,'Train detail'!$F$2:$F$181,"<="&2011) -> 25.7 | F5: =SUMIFS('Train detail'!$G$2:$G$181,'Train detail'!$B$2:$B$181,$A5,'Train detail'!$F$2:$F$181,"<="&2012) -> 25.7 | G5: =SUMIFS('Train detail'!$G$2:$G$181,'Train detail'!$B$2:$B$181,$A5,'Train detail'!$F$2:$F$181,"<="&2013) -> 25.7 | H5: =SUMIFS('Train detail'!$G$2:$G$181,'Train detail'!$B$2:$B$181,$A5,'Train detail'!$F$2:$F$181,"<="&2014) -> 25.7 | I5: =SUMIFS('Train detail'!$G$2:$G$181,'Train detail'!$B$2:$B$181,$A5,'Train detail'!$F$2:$F$181,"<="&2015) -> 25.7 | J5: =SUMIFS('Train detail'!$G$2:$G$181,'Train detail'!$B$2:$B$181,$A5,'Train detail'!$F$2:$F$181,"<="&2016) -> 25.7 | K5: =SUMIFS('Train detail'!$G$2:$G$181,'Train detail'!$B$2:$B$181,$A5,'Train detail'!$F$2:$F$181,"<="&2017) -> 30.5 | L5: =SUMIFS('Train detail'!$G$2:$G$181,'Train detail'!$B$2:$B$181,$A5,'Train detail'!$F$2:$F$181,"<="&2018) -> 30.5 | M5: =SUMIFS('Train detail'!$G$2:$G$181,'Train detail'!$B$2:$B$181,$A5,'Train detail'!$F$2:$F$181,"<="&2019) -> 30.5 | N5: =SUMIFS('Train detail'!$G$2:$G$181,'Train detail'!$B$2:$B$181,$A5,'Train detail'!$F$2:$F$181,"<="&2020) -> 30.5 | O5: =SUMIFS('Train detail'!$G$2:$G$181,'Train detail'!$B$2:$B$181,$A5,'Train detail'!$F$2:$F$181,"<="&2021) -> 32 | P5: =SUMIFS('Train detail'!$G$2:$G$181,'Train detail'!$B$2:$B$181,$A5,'Train detail'!$F$2:$F$181,"<="&2022) -> 32 | Q5: =SUMIFS('Train detail'!$G$2:$G$181,'Train detail'!$B$2:$B$181,$A5,'Train detail'!$F$2:$F$181,"<="&2023) -> 32 | R5: =SUMIFS('Train detail'!$G$2:$G$181,'Train detail'!$B$2:$B$181,$A5,'Train detail'!$F$2:$F$181,"<="&2024) -> 32 | S5: =SUMIFS('Train detail'!$G$2:$G$181,'Train detail'!$B$2:$B$181,$A5,'Train detail'!$F$2:$F$181,"<="&2025) -> 32
A6: Indonesia | B6: 1983 | C6: =SUMIFS('Train detail'!$G$2:$G$181,'Train detail'!$B$2:$B$181,$A6) -> 30.35 | D6: =SUMIFS('Train detail'!$G$2:$G$181,'Train detail'!$B$2:$B$181,$A6,'Train detail'!$F$2:$F$181,"<="&2010) -> 24.55 | E6: =SUMIFS('Train detail'!$G$2:$G$181,'Train detail'!$B$2:$B$181,$A6,'Train detail'!$F$2:$F$181,"<="&2011) -> 24.55 | F6: =SUMIFS('Train detail'!$G$2:$G$181,'Train detail'!$B$2:$B$181,$A6,'Train detail'!$F$2:$F$181,"<="&2012) -> 24.55 | G6: =SUMIFS('Train detail'!$G$2:$G$181,'Train detail'!$B$2:$B$181,$A6,'Train detail'!$F$2:$F$181,"<="&2013) -> 24.55 | H6: =SUMIFS('Train detail'!$G$2:$G$181,'Train detail'!$B$2:$B$181,$A6,'Train detail'!$F$2:$F$181,"<="&2014) -> 24.55 | I6: =SUMIFS('Train detail'!$G$2:$G$181,'Train detail'!$B$2:$B$181,$A6,'Train detail'!$F$2:$F$181,"<="&2015) -> 26.55 | J6: =SUMIFS('Train detail'!$G$2:$G$181,'Train detail'!$B$2:$B$181,$A6,'Train detail'!$F$2:$F$181,"<="&2016) -> 26.55 | K6: =SUMIFS('Train detail'!$G$2:$G$181,'Train detail'!$B$2:$B$181,$A6,'Train detail'!$F$2:$F$181,"<="&2017) -> 26.55 | L6: =SUMIFS('Train detail'!$G$2:$G$181,'Train detail'!$B$2:$B$181,$A6,'Train detail'!$F$2:$F$181,"<="&2018) -> 26.55 | M6: =SUMIFS('Train detail'!$G$2:$G$181,'Train detail'!$B$2:$B$181,$A6,'Train detail'!$F$2:$F$181,"<="&2019) -> 26.55 | N6: =SUMIFS('Train detail'!$G$2:$G$181,'Train detail'!$B$2:$B$181,$A6,'Train detail'!$F$2:$F$181,"<="&2020) -> 26.55 | O6: =SUMIFS('Train detail'!$G$2:$G$181,'Train detail'!$B$2:$B$181,$A6,'Train detail'!$F$2:$F$181,"<="&2021) -> 26.55 | P6: =SUMIFS('Train detail'!$G$2:$G$181,'Train detail'!$B$2:$B$181,$A6,'Train detail'!$F$2:$F$181,"<="&2022) -> 26.55 | Q6: =SUMIFS('Train detail'!$G$2:$G$181,'Train detail'!$B$2:$B$181,$A6,'Train detail'!$F$2:$F$181,"<="&2023) -> 30.35 | R6: =SUMIFS('Train detail'!$G$2:$G$181,'Train detail'!$B$2:$B$181,$A6,'Train detail'!$F$2:$F$181,"<="&2024) -> 30.35 | S6: =SUMIFS('Train detail'!$G$2:$G$181,'Train detail'!$B$2:$B$181,$A6,'Train detail'!$F$2:$F$181,"<="&2025) -> 30.35
A7: Australia | B7: 1989 | C7: =SUMIFS('Train detail'!$G$2:$G$181,'Train detail'!$B$2:$B$181,$A7) -> 85.1 | D7: =SUMIFS('Train detail'!$G$2:$G$181,'Train detail'!$B$2:$B$181,$A7,'Train detail'!$F$2:$F$181,"<="&2010) -> 17.9 | E7: =SUMIFS('Train detail'!$G$2:$G$181,'Train detail'!$B$2:$B$181,$A7,'Train detail'!$F$2:$F$181,"<="&2011) -> 17.9 | F7: =SUMIFS('Train detail'!$G$2:$G$181,'Train detail'!$B$2:$B$181,$A7,'Train detail'!$F$2:$F$181,"<="&2012) -> 22.8 | G7: =SUMIFS('Train detail'!$G$2:$G$181,'Train detail'!$B$2:$B$181,$A7,'Train detail'!$F$2:$F$181,"<="&2013) -> 22.8 | H7: =SUMIFS('Train detail'!$G$2:$G$181,'Train detail'!$B$2:$B$181,$A7,'Train detail'!$F$2:$F$181,"<="&2014) -> 22.8 | I7: =SUMIFS('Train detail'!$G$2:$G$181,'Train detail'!$B$2:$B$181,$A7,'Train detail'!$F$2:$F$181,"<="&2015) -> 35.2 | J7: =SUMIFS('Train detail'!$G$2:$G$181,'Train detail'!$B$2:$B$181,$A7,'Train detail'!$F$2:$F$181,"<="&2016) -> 63.7 | K7: =SUMIFS('Train detail'!$G$2:$G$181,'Train detail'!$B$2:$B$181,$A7,'Train detail'!$F$2:$F$181,"<="&2017) -> 72.6 | L7: =SUMIFS('Train detail'!$G$2:$G$181,'Train detail'!$B$2:$B$181,$A7,'Train detail'!$F$2:$F$181,"<="&2018) -> 81.5 | M7: =SUMIFS('Train detail'!$G$2:$G$181,'Train detail'!$B$2:$B$181,$A7,'Train detail'!$F$2:$F$181,"<="&2019) -> 85.1 | N7: =SUMIFS('Train detail'!$G$2:$G$181,'Train detail'!$B$2:$B$181,$A7,'Train detail'!$F$2:$F$181,"<="&2020) -> 85.1 | O7: =SUMIFS('Train detail'!$G$2:$G$181,'Train detail'!$B$2:$B$181,$A7,'Train detail'!$F$2:$F$181,"<="&2021) -> 85.1 | P7: =SUMIFS('Train detail'!$G$2:$G$181,'Train detail'!$B$2:$B$181,$A7,'Train detail'!$F$2:$F$181,"<="&2022) -> 85.1 | Q7: =SUMIFS('Train detail'!$G$2:$G$181,'Train detail'!$B$2:$B$181,$A7,'Train detail'!$F$2:$F$181,"<="&2023) -> 85.1 | R7: =SUMIFS('Train detail'!$G$2:$G$181,'Train detail'!$B$2:$B$181,$A7,'Train detail'!$F$2:$F$181,"<="&2024) -> 85.1 | S7: =SUMIFS('Train detail'!$G$2:$G$181,'Train detail'!$B$2:$B$181,$A7,'Train detail'!$F$2:$F$181,"<="&2025) -> 85.1
A8: Qatar | B8: 1996 | C8: =SUMIFS('Train detail'!$G$2:$G$181,'Train detail'!$B$2:$B$181,$A8) -> 77.1 | D8: =SUMIFS('Train detail'!$G$2:$G$181,'Train detail'!$B$2:$B$181,$A8,'Train detail'!$F$2:$F$181,"<="&2010) -> 69.3 | E8: =SUMIFS('Train detail'!$G$2:$G$181,'Train detail'!$B$2:$B$181,$A8,'Train detail'!$F$2:$F$181,"<="&2011) -> 77.1 | F8: =SUMIFS('Train detail'!$G$2:$G$181,'Train detail'!$B$2:$B$181,$A8,'Train detail'!$F$2:$F$181,"<="&2012) -> 77.1 | G8: =SUMIFS('Train detail'!$G$2:$G$181,'Train detail'!$B$2:$B$181,$A8,'Train detail'!$F$2:$F$181,"<="&2013) -> 77.1 | H8: =SUMIFS('Train detail'!$G$2:$G$181,'Train detail'!$B$2:$B$181,$A8,'Train detail'!$F$2:$F$181,"<="&2014) -> 77.1 | I8: =SUMIFS('Train detail'!$G$2:$G$181,'Train detail'!$B$2:$B$181,$A8,'Train detail'!$F$2:$F$181,"<="&2015) -> 77.1 | J8: =SUMIFS('Train detail'!$G$2:$G$181,'Train detail'!$B$2:$B$181,$A8,'Train detail'!$F$2:$F$181,"<="&2016) -> 77.1 | K8: =SUMIFS('Train detail'!$G$2:$G$181,'Train detail'!$B$2:$B$181,$A8,'Train detail'!$F$2:$F$181,"<="&2017) -> 77.1 | L8: =SUMIFS('Train detail'!$G$2:$G$181,'Train detail'!$B$2:$B$181,$A8,'Train detail'!$F$2:$F$181,"<="&2018) -> 77.1 | M8: =SUMIFS('Train detail'!$G$2:$G$181,'Train detail'!$B$2:$B$181,$A8,'Train detail'!$F$2:$F$181,"<="&2019) -> 77.1 | N8: =SUMIFS('Train detail'!$G$2:$G$181,'Train detail'!$B$2:$B$181,$A8,'Train detail'!$F$2:$F$181,"<="&2020) -> 77.1 | O8: =SUMIFS('Train detail'!$G$2:$G$181,'Train detail'!$B$2:$B$181,$A8,'Train detail'!$F$2:$F$181,"<="&2021) -> 77.1 | P8: =SUMIFS('Train detail'!$G$2:$G$181,'Train detail'!$B$2:$B$181,$A8,'Train detail'!$F$2:$F$181,"<="&2022) -> 77.1 | Q8: =SUMIFS('Train detail'!$G$2:$G$181,'Train detail'!$B$2:$B$181,$A8,'Train detail'!$F$2:$F$181,"<="&2023) -> 77.1 | R8: =SUMIFS('Train detail'!$G$2:$G$181,'Train detail'!$B$2:$B$181,$A8,'Train detail'!$F$2:$F$181,"<="&2024) -> 77.1 | S8: =SUMIFS('Train detail'!$G$2:$G$181,'Train detail'!$B$2:$B$181,$A8,'Train detail'!$F$2:$F$181,"<="&2025) -> 77.1
A9: Nigeria | B9: 1999 | C9: =SUMIFS('Train detail'!$G$2:$G$181,'Train detail'!$B$2:$B$181,$A9) -> 22.2 | D9: =SUMIFS('Train detail'!$G$2:$G$181,'Train detail'!$B$2:$B$181,$A9,'Train detail'!$F$2:$F$181,"<="&2010) -> 22.2 | E9: =SUMIFS('Train detail'!$G$2:$G$181,'Train detail'!$B$2:$B$181,$A9,'Train detail'!$F$2:$F$181,"<="&2011) -> 22.2 | F9: =SUMIFS('Train detail'!$G$2:$G$181,'Train detail'!$B$2:$B$181,$A9,'Train detail'!$F$2:$F$181,"<="&2012) -> 22.2 | G9: =SUMIFS('Train detail'!$G$2:$G$181,'Train detail'!$B$2:$B$181,$A9,'Train detail'!$F$2:$F$181,"<="&2013) -> 22.2 | H9: =SUMIFS('Train detail'!$G$2:$G$181,'Train detail'!$B$2:$B$181,$A9,'Train detail'!$F$2:$F$181,"<="&2014) -> 22.2 | I9: =SUMIFS('Train detail'!$G$2:$G$181,'Train detail'!$B$2:$B$181,$A9,'Train detail'!$F$2:$F$181,"<="&2015) -> 22.2 | J9: =SUMIFS('Train detail'!$G$2:$G$181,'Train detail'!$B$2:$B$181,$A9,'Train detail'!$F$2:$F$181,"<="&2016) -> 22.2 | K9: =SUMIFS('Train detail'!$G$2:$G$181,'Train detail'!$B$2:$B$181,$A9,'Train detail'!$F$2:$F$181,"<="&2017) -> 22.2 | L9: =SUMIFS('Train detail'!$G$2:$G$181,'Train detail'!$B$2:$B$181,$A9,'Train detail'!$F$2:$F$181,"<="&2018) -> 22.2 | M9: =SUMIFS('Train detail'!$G$2:$G$181,'Train detail'!$B$2:$B$181,$A9,'Train detail'!$F$2:$F$181,"<="&2019) -> 22.2 | N9: =SUMIFS('Train detail'!$G$2:$G$181,'Train detail'!$B$2:$B$181,$A9,'Train detail'!$F$2:$F$181,"<="&2020) -> 22.2 | O9: =SUMIFS('Train detail'!$G$2:$G$181,'Train detail'!$B$2:$B$181,$A9,'Train detail'!$F$2:$F$181,"<="&2021) -> 22.2 | P9: =SUMIFS('Train detail'!$G$2:$G$181,'Train detail'!$B$2:$B$181,$A9,'Train detail'!$F$2:$F$181,"<="&2022) -> 22.2 | Q9: =SUMIFS('Train detail'!$G$2:$G$181,'Train detail'!$B$2:$B$181,$A9,'Train detail'!$F$2:$F$181,"<="&2023) -> 22.2 | R9: =SUMIFS('Train detail'!$G$2:$G$181,'Train detail'!$B$2:$B$181,$A9,'Train detail'!$F$2:$F$181,"<="&2024) -> 22.2 | S9: =SUMIFS('Train detail'!$G$2:$G$181,'Train detail'!$B$2:$B$181,$A9,'Train detail'!$F$2:$F$181,"<="&2025) -> 22.2
A10: Oman | B10: 2000 | C10: =SUMIFS('Train detail'!$G$2:$G$181,'Train detail'!$B$2:$B$181,$A10) -> 10.4 | D10: =SUMIFS('Train detail'!$G$2:$G$181,'Train detail'!$B$2:$B$181,$A10,'Train detail'!$F$2:$F$181,"<="&2010) -> 10.4 | E10: =SUMIFS('Train detail'!$G$2:$G$181,'Train detail'!$B$2:$B$181,$A10,'Train detail'!$F$2:$F$181,"<="&2011) -> 10.4 | F10: =SUMIFS('Train detail'!$G$2:$G$181,'Train detail'!$B$2:$B$181,$A10,'Train detail'!$F$2:$F$181,"<="&2012) -> 10.4 | G10: =SUMIFS('Train detail'!$G$2:$G$181,'Train detail'!$B$2:$B$181,$A10,'Train detail'!$F$2:$F$181,"<="&2013) -> 10.4 | H10: =SUMIFS('Train detail'!$G$2:$G$181,'Train detail'!$B$2:$B$181,$A10,'Train detail'!$F$2:$F$181,"<="&2014) -> 10.4 | I10: =SUMIFS('Train detail'!$G$2:$G$181,'Train detail'!$B$2:$B$181,$A10,'Train detail'!$F$2:$F$181,"<="&2015) -> 10.4 | J10: =SUMIFS('Train detail'!$G$2:$G$181,'Train detail'!$B$2:$B$181,$A10,'Train detail'!$F$2:$F$181,"<="&2016) -> 10.4 | K10: =SUMIFS('Train detail'!$G$2:$G$181,'Train detail'!$B$2:$B$181,$A10,'Train detail'!$F$2:$F$181,"<="&2017) -> 10.4 | L10: =SUMIFS('Train detail'!$G$2:$G$181,'Train detail'!$B$2:$B$181,$A10,'Train detail'!$F$2:$F$181,"<="&2018) -> 10.4 | M10: =SUMIFS('Train detail'!$G$2:$G$181,'Train detail'!$B$2:$B$181,$A10,'Train detail'!$F$2:$F$181,"<="&2019) -> 10.4 | N10: =SUMIFS('Train detail'!$G$2:$G$181,'Train detail'!$B$2:$B$181,$A10,'Train detail'!$F$2:$F$181,"<="&2020) -> 10.4 | O10: =SUMIFS('Train detail'!$G$2:$G$181,'Train detail'!$B$2:$B$181,$A10,'Train detail'!$F$2:$F$181,"<="&2021) -> 10.4 | P10: =SUMIFS('Train detail'!$G$2:$G$181,'Train detail'!$B$2:$B$181,$A10,'Train detail'!$F$2:$F$181,"<="&2022) -> 10.4 | Q10: =SUMIFS('Train detail'!$G$2:$G$181,'Train detail'!$B$2:$B$181,$A10,'Train detail'!$F$2:$F$181,"<="&2023) -> 10.4 | R10: =SUMIFS('Train detail'!$G$2:$G$181,'Train detail'!$B$2:$B$181,$A10,'Train detail'!$F$2:$F$181,"<="&2024) -> 10.4 | S10: =SUMIFS('Train detail'!$G$2:$G$181,'Train detail'!$B$2:$B$181,$A10,'Train detail'!$F$2:$F$181,"<="&2025) -> 10.4
A11: Trinidad and Tobago | B11: 2002 | C11: =SUMIFS('Train detail'!$G$2:$G$181,'Train detail'!$B$2:$B$181,$A11) -> 11.8 | D11: =SUMIFS('Train detail'!$G$2:$G$181,'Train detail'!$B$2:$B$181,$A11,'Train detail'!$F$2:$F$181,"<="&2010) -> 11.8 | E11: =SUMIFS('Train detail'!$G$2:$G$181,'Train detail'!$B$2:$B$181,$A11,'Train detail'!$F$2:$F$181,"<="&2011) -> 11.8 | F11: =SUMIFS('Train detail'!$G$2:$G$181,'Train detail'!$B$2:$B$181,$A11,'Train detail'!$F$2:$F$181,"<="&2012) -> 11.8 | G11: =SUMIFS('Train detail'!$G$2:$G$181,'Train detail'!$B$2:$B$181,$A11,'Train detail'!$F$2:$F$181,"<="&2013) -> 11.8 | H11: =SUMIFS('Train detail'!$G$2:$G$181,'Train detail'!$B$2:$B$181,$A11,'Train detail'!$F$2:$F$181,"<="&2014) -> 11.8 | I11: =SUMIFS('Train detail'!$G$2:$G$181,'Train detail'!$B$2:$B$181,$A11,'Train detail'!$F$2:$F$181,"<="&2015) -> 11.8 | J11: =SUMIFS('Train detail'!$G$2:$G$181,'Train detail'!$B$2:$B$181,$A11,'Train detail'!$F$2:$F$181,"<="&2016) -> 11.8 | K11: =SUMIFS('Train detail'!$G$2:$G$181,'Train detail'!$B$2:$B$181,$A11,'Train detail'!$F$2:$F$181,"<="&2017) -> 11.8 | L11: =SUMIFS('Train detail'!$G$2:$G$181,'Train detail'!$B$2:$B$181,$A11,'Train detail'!$F$2:$F$181,"<="&2018) -> 11.8 | M11: =SUMIFS('Train detail'!$G$2:$G$181,'Train detail'!$B$2:$B$181,$A11,'Train detail'!$F$2:$F$181,"<="&2019) -> 11.8 | N11: =SUMIFS('Train detail'!$G$2:$G$181,'Train detail'!$B$2:$B$181,$A11,'Train detail'!$F$2:$F$181,"<="&2020) -> 11.8 | O11: =SUMIFS('Train detail'!$G$2:$G$181,'Train detail'!$B$2:$B$181,$A11,'Train detail'!$F$2:$F$181,"<="&2021) -> 11.8 | P11: =SUMIFS('Train detail'!$G$2:$G$181,'Train detail'!$B$2:$B$181,$A11,'Train detail'!$F$2:$F$181,"<="&2022) -> 11.8 | Q11: =SUMIFS('Train detail'!$G$2:$G$181,'Train detail'!$B$2:$B$181,$A11,'Train detail'!$F$2:$F$181,"<="&2023) -> 11.8 | R11: =SUMIFS('Train detail'!$G$2:$G$181,'Train detail'!$B$2:$B$181,$A11,'Train detail'!$F$2:$F$181,"<="&2024) -> 11.8 | S11: =SUMIFS('Train detail'!$G$2:$G$181,'Train detail'!$B$2:$B$181,$A11,'Train detail'!$F$2:$F$181,"<="&2025) -> 11.8
A12: Egypt | B12: 2005 | C12: =SUMIFS('Train detail'!$G$2:$G$181,'Train detail'!$B$2:$B$181,$A12) -> 12.2 | D12: =SUMIFS('Train detail'!$G$2:$G$181,'Train detail'!$B$2:$B$181,$A12,'Train detail'!$F$2:$F$181,"<="&2010) -> 12.2 | E12: =SUMIFS('Train detail'!$G$2:$G$181,'Train detail'!$B$2:$B$181,$A12,'Train detail'!$F$2:$F$181,"<="&2011) -> 12.2 | F12: =SUMIFS('Train detail'!$G$2:$G$181,'Train detail'!$B$2:$B$181,$A12,'Train detail'!$F$2:$F$181,"<="&2012) -> 12.2 | G12: =SUMIFS('Train detail'!$G$2:$G$181,'Train detail'!$B$2:$B$181,$A12,'Train detail'!$F$2:$F$181,"<="&2013) -> 12.2 | H12: =SUMIFS('Train detail'!$G$2:$G$181,'Train detail'!$B$2:$B$181,$A12,'Train detail'!$F$2:$F$181,"<="&2014) -> 12.2 | I12: =SUMIFS('Train detail'!$G$2:$G$181,'Train detail'!$B$2:$B$181,$A12,'Train detail'!$F$2:$F$181,"<="&2015) -> 12.2 | J12: =SUMIFS('Train detail'!$G$2:$G$181,'Train detail'!$B$2:$B$181,$A12,'Train detail'!$F$2:$F$181,"<="&2016) -> 12.2 | K12: =SUMIFS('Train detail'!$G$2:$G$181,'Train detail'!$B$2:$B$181,$A12,'Train detail'!$F$2:$F$181,"<="&2017) -> 12.2 | L12: =SUMIFS('Train detail'!$G$2:$G$181,'Train detail'!$B$2:$B$181,$A12,'Train detail'!$F$2:$F$181,"<="&2018) -> 12.2 | M12: =SUMIFS('Train detail'!$G$2:$G$181,'Train detail'!$B$2:$B$181,$A12,'Train detail'!$F$2:$F$181,"<="&2019) -> 12.2 | N12: =SUMIFS('Train detail'!$G$2:$G$181,'Train detail'!$B$2:$B$181,$A12,'Train detail'!$F$2:$F$181,"<="&2020) -> 12.2 | O12: =SUMIFS('Train detail'!$G$2:$G$181,'Train detail'!$B$2:$B$181,$A12,'Train detail'!$F$2:$F$181,"<="&2021) -> 12.2 | P12: =SUMIFS('Train detail'!$G$2:$G$181,'Train detail'!$B$2:$B$181,$A12,'Train detail'!$F$2:$F$181,"<="&2022) -> 12.2 | Q12: =SUMIFS('Train detail'!$G$2:$G$181,'Train detail'!$B$2:$B$181,$A12,'Train detail'!$F$2:$F$181,"<="&2023) -> 12.2 | R12: =SUMIFS('Train detail'!$G$2:$G$181,'Train detail'!$B$2:$B$181,$A12,'Train detail'!$F$2:$F$181,"<="&2024) -> 12.2 | S12: =SUMIFS('Train detail'!$G$2:$G$181,'Train detail'!$B$2:$B$181,$A12,'Train detail'!$F$2:$F$181,"<="&2025) -> 12.2
A13: Equatorial Guinea | B13: 2007 | C13: =SUMIFS('Train detail'!$G$2:$G$181,'Train detail'!$B$2:$B$181,$A13) -> 3.7 | D13: =SUMIFS('Train detail'!$G$2:$G$181,'Train detail'!$B$2:$B$181,$A13,'Train detail'!$F$2:$F$181,"<="&2010) -> 3.7 | E13: =SUMIFS('Train detail'!$G$2:$G$181,'Train detail'!$B$2:$B$181,$A13,'Train detail'!$F$2:$F$181,"<="&2011) -> 3.7 | F13: =SUMIFS('Train detail'!$G$2:$G$181,'Train detail'!$B$2:$B$181,$A13,'Train detail'!$F$2:$F$181,"<="&2012) -> 3.7 | G13: =SUMIFS('Train detail'!$G$2:$G$181,'Train detail'!$B$2:$B$181,$A13,'Train detail'!$F$2:$F$181,"<="&2013) -> 3.7 | H13: =SUMIFS('Train detail'!$G$2:$G$181,'Train detail'!$B$2:$B$181,$A13,'Train detail'!$F$2:$F$181,"<="&2014) -> 3.7 | I13: =SUMIFS('Train detail'!$G$2:$G$181,'Train detail'!$B$2:$B$181,$A13,'Train detail'!$F$2:$F$181,"<="&2015) -> 3.7 | J13: =SUMIFS('Train detail'!$G$2:$G$181,'Train detail'!$B$2:$B$181,$A13,'Train detail'!$F$2:$F$181,"<="&2016) -> 3.7 | K13: =SUMIFS('Train detail'!$G$2:$G$181,'Train detail'!$B$2:$B$181,$A13,'Train detail'!$F$2:$F$181,"<="&2017) -> 3.7 | L13: =SUMIFS('Train detail'!$G$2:$G$181,'Train detail'!$B$2:$B$181,$A13,'Train detail'!$F$2:$F$181,"<="&2018) -> 3.7 | M13: =SUMIFS('Train detail'!$G$2:$G$181,'Train detail'!$B$2:$B$181,$A13,'Train detail'!$F$2:$F$181,"<="&2019) -> 3.7 | N13: =SUMIFS('Train detail'!$G$2:$G$181,'Train detail'!$B$2:$B$181,$A13,'Train detail'!$F$2:$F$181,"<="&2020) -> 3.7 | O13: =SUMIFS('Train detail'!$G$2:$G$181,'Train detail'!$B$2:$B$181,$A13,'Train detail'!$F$2:$F$181,"<="&2021) -> 3.7 | P13: =SUMIFS('Train detail'!$G$2:$G$181,'Train detail'!$B$2:$B$181,$A13,'Train detail'!$F$2:$F$181,"<="&2022) -> 3.7 | Q13: =SUMIFS('Train detail'!$G$2:$G$181,'Train detail'!$B$2:$B$181,$A13,'Train detail'!$F$2:$F$181,"<="&2023) -> 3.7 | R13: =SUMIFS('Train detail'!$G$2:$G$181,'Train detail'!$B$2:$B$181,$A13,'Train detail'!$F$2:$F$181,"<="&2024) -> 3.7 | S13: =SUMIFS('Train detail'!$G$2:$G$181,'Train detail'!$B$2:$B$181,$A13,'Train detail'!$F$2:$F$181,"<="&2025) -> 3.7
... A27: Mauritania | B27: 2025 | C27: =SUMIFS('Train detail'!$G$2:$G$181,'Train detail'!$B$2:$B$181,$A27) -> 2.5 | D27: =SUMIFS('Train detail'!$G$2:$G$181,'Train detail'!$B$2:$B$181,$A27,'Train detail'!$F$2:$F$181,"<="&2010) -> 0 | E27: =SUMIFS('Train detail'!$G$2:$G$181,'Train detail'!$B$2:$B$181,$A27,'Train detail'!$F$2:$F$181,"<="&2011) -> 0 | F27: =SUMIFS('Train detail'!$G$2:$G$181,'Train detail'!$B$2:$B$181,$A27,'Train detail'!$F$2:$F$181,"<="&2012) -> 0 | G27: =SUMIFS('Train detail'!$G$2:$G$181,'Train detail'!$B$2:$B$181,$A27,'Train detail'!$F$2:$F$181,"<="&2013) -> 0 | H27: =SUMIFS('Train detail'!$G$2:$G$181,'Train detail'!$B$2:$B$181,$A27,'Train detail'!$F$2:$F$181,"<="&2014) -> 0 | I27: =SUMIFS('Train detail'!$G$2:$G$181,'Train detail'!$B$2:$B$181,$A27,'Train detail'!$F$2:$F$181,"<="&2015) -> 0 | J27: =SUMIFS('Train detail'!$G$2:$G$181,'Train detail'!$B$2:$B$181,$A27,'Train detail'!$F$2:$F$181,"<="&2016) -> 0 | K27: =SUMIFS('Train detail'!$G$2:$G$181,'Train detail'!$B$2:$B$181,$A27,'Train detail'!$F$2:$F$181,"<="&2017) -> 0 | L27: =SUMIFS('Train detail'!$G$2:$G$181,'Train detail'!$B$2:$B$181,$A27,'Train detail'!$F$2:$F$181,"<="&2018) -> 0 | M27: =SUMIFS('Train detail'!$G$2:$G$181,'Train detail'!$B$2:$B$181,$A27,'Train detail'!$F$2:$F$181,"<="&2019) -> 0 | N27: =SUMIFS('Train detail'!$G$2:$G$181,'Train detail'!$B$2:$B$181,$A27,'Train detail'!$F$2:$F$181,"<="&2020) -> 0 | O27: =SUMIFS('Train detail'!$G$2:$G$181,'Train detail'!$B$2:$B$181,$A27,'Train detail'!$F$2:$F$181,"<="&2021) -> 0 | P27: =SUMIFS('Train detail'!$G$2:$G$181,'Train detail'!$B$2:$B$181,$A27,'Train detail'!$F$2:$F$181,"<="&2022) -> 0 | Q27: =SUMIFS('Train detail'!$G$2:$G$181,'Train detail'!$B$2:$B$181,$A27,'Train detail'!$F$2:$F$181,"<="&2023) -> 0 | R27: =SUMIFS('Train detail'!$G$2:$G$181,'Train detail'!$B$2:$B$181,$A27,'Train detail'!$F$2:$F$181,"<="&2024) -> 0 | S27: =SUMIFS('Train detail'!$G$2:$G$181,'Train detail'!$B$2:$B$181,$A27,'Train detail'!$F$2:$F$181,"<="&2025) -> 2.5
A28: GLOBAL TOTAL | C28: =SUM(C2:C27) -> 524.552 | D28: =SUM(D2:D27) -> 255.77 | E28: =SUM(E2:E27) -> 263.57 | F28: =SUM(F2:F27) -> 268.47 | G28: =SUM(G2:G27) -> 278.17 | H28: =SUM(H2:H27) -> 289.77 | I28: =SUM(I2:I27) -> 304.17 | J28: =SUM(J2:J27) -> 342.67 | ... S28: =SUM(S2:S27) -> 524.552

Sheet Under construction
A1: RefNo | B1: Country | C1: Terminal | D1: Train | E1: Technology | F1: Expected Start | G1: Capacity (Mtpa) | H1: Ownership
A2: 42 | B2: United States | C2: Corpus Christi LNG | D2: Corpus Christi Stage 3 T5 | E2: Chart Industries IPSMR | F2: 2026 | G2: 1.49 | H2: Cheniere Energy (100%)
A3: 42 | B3: United States | C3: Corpus Christi LNG | D3: Corpus Christi Stage 3 T6 | E3: Chart Industries IPSMR | F3: 2026 | G3: 1.49 | H3: Cheniere Energy (100%)
A4: 42 | B4: United States | C4: Corpus Christi LNG | D4: Corpus Christi Stage 3 T7 | E4: Chart Industries IPSMR | F4: 2026 | G4: 1.49 | H4: Cheniere Energy (100%)
A5: 50 | B5: Congo | C5: Congo Marine XII FLNG | D5: Congo Marine XII FLNG 2 | E5: Chart Industries IPSMR | F5: 2026 | G5: 2.4 | H5: Eni (100%)
A6: 55 | B6: United States | C6: Golden Pass LNG | D6: Golden Pass LNG T1 | E6: AP-C3MR | F6: 2026 | G6: 6 | H6: ExxonMobil (30%); QatarEnergy (70%)
A7: 56 | B7: Mexico | C7: Energía Costa Azul LNG | D7: Energía Costa Azul LNG T1 | E7: AP-DMR | F7: 2026 | G7: 3.25 | H7: Sempra (83.4%); TotalEnergies (16.6%)
A8: 53 | B8: Canada | C8: LNG Canada | D8: LNG Canada T2 | E8: Shell DMR | F8: 2025 | G8: 7 | H8: Shell* (40%); Petronas (20%); MidOcean Energy (5%); Mitsubishi Corp (15%); PetroChina (15%); Korea Gas (5%)
A9: 8 | B9: Qatar | C9: QatarGas LNG | D9: QatarGas LNG T8 | E9: AP-X | F9: 2027 | G9: 7.8 | H9: CNPC (parent) (1.25%); ConocoPhillips (3.125%); CPC Corporation (1.25%); Eni (3.125%); ExxonMobil (6.25%); QatarEnergy (71.25%); Shell (6.25%); Sinopec Group (parent) (1.25%); TotalEnergies (6.25%)
A10: 10 | B10: Nigeria | C10: NLNG | D10: NLNG T7 | E10: AP-C3MR | F10: 2027 | G10: 8 | H10: Eni (10.4%); NNPC (Nigeria) (49%); Shell (25.6%); TotalEnergies (15%)
A11: 21 | B11: Australia | C11: Pluto LNG | D11: Pluto LNG T2 (expansion) | E11: ConocoPhillips Optimized Cascade | F11: 2027 | G11: 5 | H11: Global Infrastructure Partners (GIP) (49%); Woodside (51%)
A12: 48 | B12: Mexico | C12: Altamira LNG | D12: Altamira LNG T2 | E12: Chart Industries IPSMR | F12: 2027 | G12: 1.4 | H12: New Fortress Energy (100%)
A13: 55 | B13: United States | C13: Golden Pass LNG | D13: Golden Pass LNG T2 | E13: AP-C3MR | F13: 2027 | G13: 6 | H13: ExxonMobil (30%); QatarEnergy (70%)
... A76: 69 | B76: United States | C76: Woodside Louisiana LNG | D76: Woodside Louisiana LNG T2 | E76: Chart Industries IPSMR | F76: 2030 | G76: 5.5 | H76: Woodside (60%); Stonepeak (40%)
A77: IMO Number | B77: Name | C77: Shipowner | D77: Shipbuilder | E77: Capacity (cm) | F77: Cargo Type | G77: Vessel Type | H77: Propulsion Type
A78: 9443401 | B78: Aamira | C78: Nakilat | D78: HD Hyundai | E78: 266000 | F78: Membrane | G78: Q-Max | H78: SSD
A79: 9501186 | B79: Adam LNG | C79: Asyad Shipping | D79: HD Hyundai | E79: 162000 | F79: Membrane | G79: Conventional | H79: DFDE
A80: 9879698 | B80: Adamastos | C80: Capital Gas | D80: HD Hyundai | E80: 174000 | F80: Membrane | G80: Conventional | H80: X-DF
A81: 9831220 | B81: Adriano Knutsen | C81: Knutsen OAS | D81: HD Hyundai | E81: 180000 | F81: Membrane | G81: Conventional | H81: ME-GI
A82: 9958286 | B82: Aktoras | C82: Capital Gas | D82: HD Hyundai | E82: 174000 | F82: Membrane | G82: Conventional | H82: ME-GA
A83: 9338266 | B83: Al Aamriya | C83: NYK Line, K Line, MOL, lino, Mitsui, Nakilat | D83: Hanwha Ocean | E83: 216200 | F83: Membrane | G83: Q-Flex | H83: SSD
A84: 9325697 | B84: Al Areesh | C84: Seapeak | D84: Hanwha Ocean | E84: 151700 | F84: Membrane | G84: Conventional | H84: Steam
A85: 9431147 | B85: Al Bahiya | C85: Nakilat | D85: Hanwha Ocean | E85: 210100 | F85: Membrane | G85: Q-Flex | H85: SSD
A86: 9132741 | B86: Al Bidda | C86: J4 Consortium | D86: Kawasaki | E86: 137300 | F86: Spherical | G86: Conventional | H86: Steam
A87: 9325702 | B87: Al Daayen | C87: Seapeak | D87: Hanwha Ocean | E87: 151700 | F87: Membrane | G87: Conventional | H87: Steam
A88: 9443683 | B88: Al Dafna | C88: Nakilat | D88: Samsung | E88: 266400 | F88: Membrane | G88: Q-Max | H88: SSD
... A114: 9337951 | B114: Al Ruwais | C114: Commerz Real, Nakilat, PRONAV | D114: Hanwha Ocean | E114: 210200 | F114: Membrane | G114: Q-Flex | H114: SSD

Sheet Additions (monthly)
A1: Month | B1: MonthKey | C1: Country | D1: Terminal | E1: Capacity added (Mtpa) | F1: Note
A2: 40179 | B2: 201001 | C2: Algeria | D2: Arzew GL1Z | E2: 7.9 | F2: Pre-2010 baseline (online before Jan 2010)
A3: 40179 | B3: 201001 | C3: Algeria | D3: Arzew GL2Z | E3: 8.4 | F3: Pre-2010 baseline (online before Jan 2010)
A4: 40179 | B4: 201001 | C4: Australia | D4: Darwin LNG | E4: 3.7 | F4: Pre-2010 baseline (online before Jan 2010)
A5: 40179 | B5: 201001 | C5: Australia | D5: North West Shelf LNG | E5: 14.2 | F5: Pre-2010 baseline (online before Jan 2010)
A6: 40179 | B6: 201001 | C6: Brunei | D6: Brunei LNG | E6: 7.2 | F6: Pre-2010 baseline (online before Jan 2010)
A7: 40179 | B7: 201001 | C7: China | D7: Inland facilities | E7: 3.87 | F7: No start year in source; small-scale aggregate, placed at series start
A8: 40179 | B8: 201001 | C8: Egypt | D8: Damietta LNG | E8: 5 | F8: Pre-2010 baseline (online before Jan 2010)
A9: 40179 | B9: 201001 | C9: Egypt | D9: Egyptian LNG (Idku) | E9: 7.2 | F9: Pre-2010 baseline (online before Jan 2010)
A10: 40179 | B10: 201001 | C10: Equatorial Guinea | D10: EG LNG | E10: 3.7 | F10: Pre-2010 baseline (online before Jan 2010)
A11: 40179 | B11: 201001 | C11: Indonesia | D11: Bontang LNG | E11: 16.95 | F11: Pre-2010 baseline (online before Jan 2010)
A12: 40179 | B12: 201001 | C12: Indonesia | D12: Tangguh LNG | E12: 7.6 | F12: Pre-2010 baseline (online before Jan 2010)
A13: 40179 | B13: 201001 | C13: Malaysia | D13: MLNG | E13: 25.7 | F13: Pre-2010 baseline (online before Jan 2010)
... A106: 46327 | B106: 202611 | C106: United States | D106: Corpus Christi LNG | E106: 1.49 | F106: Stage 3 Train 7 — SC expected end-2026

Sheet Outages (event ledger)
A1: Terminal | B1: Country | C1: Type | D1: Start | E1: StartKey | F1: End | G1: EndKey | H1: Est. Mtpa offline | I1: Conf. | J1: Cause | K1: Notes (estimation basis) | L1: Source
A2: Bontang LNG | B2: Indonesia | C2: Feedgas/structural | D2: 40179 | E2: 201001 | F2: 46357 | G2: 202612 | H2: 8 | I2: L | J2: Structural feedgas decline (field depletion) | K2: Chronic underutilization of ~17 Mtpa complex; rough estimate, not a discrete outage [carried forward through 2026] | L2: https://www.gem.wiki/Bontang_LNG_Terminal
A3: Damietta LNG | B3: Egypt | C3: Feedgas/structural | D3: 41275 | E3: 201301 | F3: 44228 | G3: 202102 | H3: 5 | I3: M | J3: Idled — feedgas diverted to domestic market | K3: ~5 Mtpa idle from ~2012/13; restart Feb 2021 | L3: https://www.eni.com/en-IT/media/press-release/2021/03/eni-closes-agreement-partners-restart-damietta-liquefied-natural-gas-plant-egypt.html
A4: NLNG | B4: Nigeria | C4: Feedgas/structural | D4: 41275 | E4: 201301 | F4: 42705 | G4: 201612 | H4: 3.5 | I4: L | J4: Chronic feedgas shortfall / pipeline vandalism | K4: Ran below nameplate; magnitude estimated | L4: https://www.naturalgasintel.com/news/nigerias-lng-output-still-weak-despite-europes-thirst-for-spot-supplies/
A5: Egyptian LNG (Idku) | B5: Egypt | C5: Feedgas/structural | D5: 41426 | E5: 201306 | F5: 43435 | G5: 201812 | H5: 5 | I5: M | J5: Domestic gas shortage — exports near zero | K5: ~7.2 Mtpa plant largely idle; magnitude estimated | L5: https://www.gem.wiki/Egyptian_LNG_Terminal
A6: Angola LNG | B6: Angola | C6: Technical | D6: 41730 | E6: 201404 | F6: 42491 | G6: 201605 | H6: 5.2 | I6: H | J6: Pipeline/technical failure — full shutdown | K6: Offline ~2 yrs; first post-shutdown cargo Jun 2016 | L6: https://www.angolalng.com/news/angola-lng-loads-first-cargo-following-shutdown
A7: Yemen LNG | B7: Yemen | C7: War/conflict | D7: 42095 | E7: 201504 | F7: 46357 | G7: 202612 | H7: 6.7 | I7: H | J7: Civil war — force majeure/security shutdown (NOT sanctions) | K7: FM Apr 2015; plant essentially offline continuously through 2025 [carried forward through 2026] | L7: https://www.lngindustry.com/liquefaction/14042015/yemen-lng-halts-production-586/
A8: Gorgon LNG | B8: Australia | C8: Reliability | D8: 42430 | E8: 201603 | F8: 42552 | G8: 201607 | H8: 5.2 | I8: M | J8: Startup teething — propane circuit breakdown | K8: 1 train (~5.2) down >3 months after first cargo; dates approx | L8: https://www.boilingcold.com.au/gorgons-catastrophic-startup/
A9: North West Shelf LNG | B9: Australia | C9: Technical | D9: 43040 | E9: 201711 | F9: 43040 | G9: 201711 | H9: 2.5 | I9: L | J9: Partial unplanned outage (Friday trip) | K9: Brief partial; quickly resumed | L9: https://spglobal.com/platts/en/market-insights/latest-news/natural-gas/111217-australias-north-west-shelf-lng-hit-by-partial-outage-friday-woodside
A10: Yamal LNG | B10: Russia | C10: Technical | D10: 43252 | E10: 201806 | F10: 43800 | G10: 201912 | H10: 0.5 | I10: L | J10: Minor unplanned ramp-up trips | K10: Ran at/above nameplate overall; losses immaterial | L10: https://www.gem.wiki/Yamal_LNG_Terminal
A11: Prelude FLNG | B11: Australia | C11: Technical | D11: 43862 | E11: 202002 | F11: 44197 | G11: 202101 | H11: 3.6 | I11: H | J11: Feb 2020 electrical trip after safety incidents | K11: Whole unit offline most of 2020; cargoes resumed Jan 2021 | L11: https://www.gem.wiki/Prelude_FLNG_Terminal
A12: Peru LNG | B12: Peru | C12: Other | D12: 43922 | E12: 202004 | F12: 43983 | G12: 202006 | H12: 1 | I12: L | J12: COVID-19 + domestic gas; reduced cargoes | K12: Partial reduction, not full halt | L12: https://www.energyintel.com/0000017b-a7da-de4c-a17b-e7dacb410000
A13: Gorgon LNG | B13: Australia | C13: Technical | D13: 43952 | E13: 202005 | F13: 44075 | G13: 202009 | H13: 5.2 | I13: H | J13: Propane heat-exchanger weld cracks (T2) | K13: T2 shut late-May; restart deferred to ~Sep/Oct | L13: https://www.nsenergybusiness.com/news/gordon-lng-project-train-2-update/
... A65: Freeport LNG | B65: United States | C65: Technical | D65: 46143 | E65: 202605 | F65: 46143 | G65: 202605 | H65: 4 | I65: L | J65: Unplanned — brief Train 1 shutdown / reduced output | K65: ~3 cargoes cancelled early-mid May 2026; root cause unclear (separate from planned Jul turnaround) | L65: https://pgjonline.com/news/2026/may/freeport-lng-takes-export-train-offline-in-texas
